{
"meta":{"test_sets":[],"test_metrics":[],"learn_metrics":[{"best_value":"Min","name":"RMSE"}],"launch_mode":"Train","parameters":"","iteration_count":1000,"learn_sets":["learn"],"name":"experiment"},
"iterations":[
{"learn":[61.64931443],"iteration":0,"passed_time":0.1552836508,"remaining_time":155.1283672},
{"learn":[59.45485165],"iteration":1,"passed_time":0.1730088471,"remaining_time":86.33141471},
{"learn":[57.50748686],"iteration":2,"passed_time":0.1915971404,"remaining_time":63.67411631},
{"learn":[55.77510074],"iteration":3,"passed_time":0.2092519465,"remaining_time":52.10373467},
{"learn":[54.26155683],"iteration":4,"passed_time":0.2273148877,"remaining_time":45.23566264},
{"learn":[52.91972596],"iteration":5,"passed_time":0.2442751356,"remaining_time":40.46824747},
{"learn":[51.75058199],"iteration":6,"passed_time":0.2608305646,"remaining_time":37.00067866},
{"learn":[50.72754634],"iteration":7,"passed_time":0.2784424511,"remaining_time":34.52686393},
{"learn":[49.79878831],"iteration":8,"passed_time":0.296730791,"remaining_time":32.6733571},
{"learn":[48.98333521],"iteration":9,"passed_time":0.3128422097,"remaining_time":30.97137876},
{"learn":[48.26367509],"iteration":10,"passed_time":0.329186414,"remaining_time":29.59685122},
{"learn":[47.62554736],"iteration":11,"passed_time":0.3459109115,"remaining_time":28.47999838},
{"learn":[47.07332696],"iteration":12,"passed_time":0.3631684144,"remaining_time":27.57286347},
{"learn":[46.57853128],"iteration":13,"passed_time":0.3800389658,"remaining_time":26.76560145},
{"learn":[46.1369054],"iteration":14,"passed_time":0.3967578672,"remaining_time":26.05376661},
{"learn":[45.74502914],"iteration":15,"passed_time":0.4139745442,"remaining_time":25.45943447},
{"learn":[45.39150776],"iteration":16,"passed_time":0.4328107191,"remaining_time":25.02664334},
{"learn":[45.08624161],"iteration":17,"passed_time":0.4500264093,"remaining_time":24.55144077},
{"learn":[44.81302225],"iteration":18,"passed_time":0.4667187624,"remaining_time":24.09742663},
{"learn":[44.56649693],"iteration":19,"passed_time":0.4829152633,"remaining_time":23.6628479},
{"learn":[44.3582837],"iteration":20,"passed_time":0.499191484,"remaining_time":23.27183156},
{"learn":[44.15644172],"iteration":21,"passed_time":0.5151487335,"remaining_time":22.90070279},
{"learn":[43.96451852],"iteration":22,"passed_time":0.5315198297,"remaining_time":22.57803798},
{"learn":[43.79814145],"iteration":23,"passed_time":0.547628311,"remaining_time":22.27021798},
{"learn":[43.64548458],"iteration":24,"passed_time":0.5642687909,"remaining_time":22.00648284},
{"learn":[43.51121285],"iteration":25,"passed_time":0.5804432956,"remaining_time":21.74429884},
{"learn":[43.37850666],"iteration":26,"passed_time":0.5961450498,"remaining_time":21.48330124},
{"learn":[43.26729687],"iteration":27,"passed_time":0.6137816711,"remaining_time":21.3069923},
{"learn":[43.1624879],"iteration":28,"passed_time":0.6313403703,"remaining_time":21.13901723},
{"learn":[43.0582852],"iteration":29,"passed_time":0.6472480601,"remaining_time":20.92768728},
{"learn":[42.9583565],"iteration":30,"passed_time":0.6641744768,"remaining_time":20.76080864},
{"learn":[42.88466492],"iteration":31,"passed_time":0.6798584245,"remaining_time":20.56571734},
{"learn":[42.80643758],"iteration":32,"passed_time":0.6957454138,"remaining_time":20.38744894},
{"learn":[42.73197637],"iteration":33,"passed_time":0.7123593002,"remaining_time":20.23938482},
{"learn":[42.65181132],"iteration":34,"passed_time":0.7304014466,"remaining_time":20.13821131},
{"learn":[42.58233487],"iteration":35,"passed_time":0.7457925335,"remaining_time":19.97066673},
{"learn":[42.51332755],"iteration":36,"passed_time":0.7622719942,"remaining_time":19.8396738},
{"learn":[42.45169781],"iteration":37,"passed_time":0.7778858991,"remaining_time":19.69279566},
{"learn":[42.3930122],"iteration":38,"passed_time":0.8002851142,"remaining_time":19.71984602},
{"learn":[42.33286745],"iteration":39,"passed_time":0.8166311871,"remaining_time":19.59914849},
{"learn":[42.27518262],"iteration":40,"passed_time":0.8353135276,"remaining_time":19.53818715},
{"learn":[42.21766774],"iteration":41,"passed_time":0.8510363805,"remaining_time":19.41173458},
{"learn":[42.17401398],"iteration":42,"passed_time":0.8673181415,"remaining_time":19.30287119},
{"learn":[42.13507972],"iteration":43,"passed_time":0.8830913685,"remaining_time":19.18716701},
{"learn":[42.08903086],"iteration":44,"passed_time":0.8990969369,"remaining_time":19.08083499},
{"learn":[42.0364252],"iteration":45,"passed_time":0.9153180372,"remaining_time":18.98290016},
{"learn":[41.98091694],"iteration":46,"passed_time":0.9324435492,"remaining_time":18.9067809},
{"learn":[41.93448674],"iteration":47,"passed_time":0.9496031828,"remaining_time":18.83379646},
{"learn":[41.90156839],"iteration":48,"passed_time":0.9711872614,"remaining_time":18.84896093},
{"learn":[41.8649688],"iteration":49,"passed_time":0.9887292746,"remaining_time":18.78585622},
{"learn":[41.83310595],"iteration":50,"passed_time":1.007040922,"remaining_time":18.73885951},
{"learn":[41.8054736],"iteration":51,"passed_time":1.023501234,"remaining_time":18.65921481},
{"learn":[41.75463861],"iteration":52,"passed_time":1.044466625,"remaining_time":18.66245082},
{"learn":[41.69958208],"iteration":53,"passed_time":1.06486221,"remaining_time":18.65480835},
{"learn":[41.66228662],"iteration":54,"passed_time":1.081775012,"remaining_time":18.58686156},
{"learn":[41.62100096],"iteration":55,"passed_time":1.099535512,"remaining_time":18.5350272},
{"learn":[41.58458096],"iteration":56,"passed_time":1.114845081,"remaining_time":18.44384056},
{"learn":[41.55003895],"iteration":57,"passed_time":1.132656578,"remaining_time":18.39590512},
{"learn":[41.5257156],"iteration":58,"passed_time":1.148946957,"remaining_time":18.32473029},
{"learn":[41.49948424],"iteration":59,"passed_time":1.164446426,"remaining_time":18.242994},
{"learn":[41.4680602],"iteration":60,"passed_time":1.182075714,"remaining_time":18.19621468},
{"learn":[41.43205535],"iteration":61,"passed_time":1.199979426,"remaining_time":18.15452744},
{"learn":[41.39166403],"iteration":62,"passed_time":1.219175586,"remaining_time":18.13281784},
{"learn":[41.37018827],"iteration":63,"passed_time":1.236407959,"remaining_time":18.0824664},
{"learn":[41.32563889],"iteration":64,"passed_time":1.256119946,"remaining_time":18.0688023},
{"learn":[41.27452506],"iteration":65,"passed_time":1.274566968,"remaining_time":18.03705376},
{"learn":[41.24888311],"iteration":66,"passed_time":1.289953001,"remaining_time":17.96307686},
{"learn":[41.20604671],"iteration":67,"passed_time":1.307506089,"remaining_time":17.92052463},
{"learn":[41.16875063],"iteration":68,"passed_time":1.324403556,"remaining_time":17.86985089},
{"learn":[41.14038125],"iteration":69,"passed_time":1.341145866,"remaining_time":17.81808078},
{"learn":[41.10418078],"iteration":70,"passed_time":1.357277275,"remaining_time":17.75930406},
{"learn":[41.06537445],"iteration":71,"passed_time":1.375281252,"remaining_time":17.72584725},
{"learn":[41.03796915],"iteration":72,"passed_time":1.391559006,"remaining_time":17.67089313},
{"learn":[41.00273385],"iteration":73,"passed_time":1.408720284,"remaining_time":17.62804031},
{"learn":[40.98154933],"iteration":74,"passed_time":1.42634633,"remaining_time":17.59160474},
{"learn":[40.96179772],"iteration":75,"passed_time":1.44485863,"remaining_time":17.56643913},
{"learn":[40.93716375],"iteration":76,"passed_time":1.466001885,"remaining_time":17.57298363},
{"learn":[40.90020893],"iteration":77,"passed_time":1.483302208,"remaining_time":17.53339276},
{"learn":[40.85580715],"iteration":78,"passed_time":1.500084622,"remaining_time":17.48832831},
{"learn":[40.82693945],"iteration":79,"passed_time":1.517607393,"remaining_time":17.45248502},
{"learn":[40.7950087],"iteration":80,"passed_time":1.533554035,"remaining_time":17.39921183},
{"learn":[40.76705222],"iteration":81,"passed_time":1.550386742,"remaining_time":17.35676865},
{"learn":[40.75101066],"iteration":82,"passed_time":1.566247668,"remaining_time":17.30420617},
{"learn":[40.7347795],"iteration":83,"passed_time":1.582314342,"remaining_time":17.25476116},
{"learn":[40.68323632],"iteration":84,"passed_time":1.599298158,"remaining_time":17.21597429},
{"learn":[40.65786903],"iteration":85,"passed_time":1.614872811,"remaining_time":17.16271801},
{"learn":[40.64035575],"iteration":86,"passed_time":1.630174076,"remaining_time":17.10745898},
{"learn":[40.62211659],"iteration":87,"passed_time":1.646046554,"remaining_time":17.05902793},
{"learn":[40.60077982],"iteration":88,"passed_time":1.662063614,"remaining_time":17.01280845},
{"learn":[40.5451633],"iteration":89,"passed_time":1.678979738,"remaining_time":16.97635069},
{"learn":[40.52056974],"iteration":90,"passed_time":1.696904322,"remaining_time":16.95039592},
{"learn":[40.49768712],"iteration":91,"passed_time":1.713121101,"remaining_time":16.90776044},
{"learn":[40.48062421],"iteration":92,"passed_time":1.729461856,"remaining_time":16.86690219},
{"learn":[40.43671084],"iteration":93,"passed_time":1.746253746,"remaining_time":16.83091377},
{"learn":[40.40335813],"iteration":94,"passed_time":1.764499768,"remaining_time":16.809182},
{"learn":[40.37818713],"iteration":95,"passed_time":1.780654396,"remaining_time":16.76782889},
{"learn":[40.35730575],"iteration":96,"passed_time":1.797581714,"remaining_time":16.73418854},
{"learn":[40.33145895],"iteration":97,"passed_time":1.814625105,"remaining_time":16.7019576},
{"learn":[40.30954514],"iteration":98,"passed_time":1.831291006,"remaining_time":16.66659794},
{"learn":[40.28058543],"iteration":99,"passed_time":1.848584819,"remaining_time":16.63726337},
{"learn":[40.2316388],"iteration":100,"passed_time":1.864467473,"remaining_time":16.59560652},
{"learn":[40.21622374],"iteration":101,"passed_time":1.880666346,"remaining_time":16.55723901},
{"learn":[40.17533085],"iteration":102,"passed_time":1.897992549,"remaining_time":16.52911958},
{"learn":[40.15430401],"iteration":103,"passed_time":1.913802975,"remaining_time":16.48814871},
{"learn":[40.14447955],"iteration":104,"passed_time":1.929403086,"remaining_time":16.4458644},
{"learn":[40.13157256],"iteration":105,"passed_time":1.94525593,"remaining_time":16.4062151},
{"learn":[40.10963476],"iteration":106,"passed_time":1.961718495,"remaining_time":16.37209922},
{"learn":[40.06903994],"iteration":107,"passed_time":1.978666133,"remaining_time":16.34231658},
{"learn":[40.03629963],"iteration":108,"passed_time":1.995646634,"remaining_time":16.31303808},
{"learn":[40.01765047],"iteration":109,"passed_time":2.013846102,"remaining_time":16.29384573},
{"learn":[39.99544469],"iteration":110,"passed_time":2.030971951,"remaining_time":16.26607266},
{"learn":[39.96581116],"iteration":111,"passed_time":2.047899905,"remaining_time":16.23692068},
{"learn":[39.93426674],"iteration":112,"passed_time":2.065048252,"remaining_time":16.20971504},
{"learn":[39.88851754],"iteration":113,"passed_time":2.082109487,"remaining_time":16.18200882},
{"learn":[39.86961925],"iteration":114,"passed_time":2.098141337,"remaining_time":16.14656594},
{"learn":[39.84198718],"iteration":115,"passed_time":2.116721322,"remaining_time":16.13087628},
{"learn":[39.81163123],"iteration":116,"passed_time":2.133722077,"remaining_time":16.10321875},
{"learn":[39.79498113],"iteration":117,"passed_time":2.150344943,"remaining_time":16.07291728},
{"learn":[39.77890363],"iteration":118,"passed_time":2.168160181,"remaining_time":16.05167327},
{"learn":[39.75375279],"iteration":119,"passed_time":2.18500376,"remaining_time":16.0233609},
{"learn":[39.72879559],"iteration":120,"passed_time":2.201807684,"remaining_time":15.99495004},
{"learn":[39.72372631],"iteration":121,"passed_time":2.218315262,"remaining_time":15.96459672},
{"learn":[39.67365991],"iteration":122,"passed_time":2.236089458,"remaining_time":15.94349963},
{"learn":[39.64687862],"iteration":123,"passed_time":2.253972401,"remaining_time":15.92322438},
{"learn":[39.61715415],"iteration":124,"passed_time":2.270388627,"remaining_time":15.89272039},
{"learn":[39.59705699],"iteration":125,"passed_time":2.286935104,"remaining_time":15.8633435},
{"learn":[39.57492035],"iteration":126,"passed_time":2.303527007,"remaining_time":15.83448092},
{"learn":[39.55596975],"iteration":127,"passed_time":2.320095724,"remaining_time":15.80565212},
{"learn":[39.53261037],"iteration":128,"passed_time":2.336942715,"remaining_time":15.77889228},
{"learn":[39.51120498],"iteration":129,"passed_time":2.352949446,"remaining_time":15.74666168},
{"learn":[39.48734056],"iteration":130,"passed_time":2.36993432,"remaining_time":15.72116736},
{"learn":[39.47358227],"iteration":131,"passed_time":2.385955112,"remaining_time":15.6894624},
{"learn":[39.45922254],"iteration":132,"passed_time":2.401155284,"remaining_time":15.65264385},
{"learn":[39.42847756],"iteration":133,"passed_time":2.417402277,"remaining_time":15.62291322},
{"learn":[39.40800609],"iteration":134,"passed_time":2.435254545,"remaining_time":15.60366801},
{"learn":[39.38816116],"iteration":135,"passed_time":2.451734052,"remaining_time":15.57572221},
{"learn":[39.3496057],"iteration":136,"passed_time":2.468684005,"remaining_time":15.55090728},
{"learn":[39.30878807],"iteration":137,"passed_time":2.486067423,"remaining_time":15.5289139},
{"learn":[39.27970703],"iteration":138,"passed_time":2.50563494,"remaining_time":15.52051571},
{"learn":[39.24798832],"iteration":139,"passed_time":2.522075972,"remaining_time":15.4927524},
{"learn":[39.20407685],"iteration":140,"passed_time":2.539828031,"remaining_time":15.47313673},
{"learn":[39.17495627],"iteration":141,"passed_time":2.55625034,"remaining_time":15.44551262},
{"learn":[39.15417429],"iteration":142,"passed_time":2.574257938,"remaining_time":15.42754583},
{"learn":[39.12596601],"iteration":143,"passed_time":2.591465469,"remaining_time":15.40482251},
{"learn":[39.11247889],"iteration":144,"passed_time":2.609536738,"remaining_time":15.38726835},
{"learn":[39.09591597],"iteration":145,"passed_time":2.627041513,"remaining_time":15.3663935},
{"learn":[39.06988805],"iteration":146,"passed_time":2.646046103,"remaining_time":15.35426752},
{"learn":[39.05110293],"iteration":147,"passed_time":2.664277952,"remaining_time":15.3376001},
{"learn":[39.0086131],"iteration":148,"passed_time":2.68234643,"remaining_time":15.3199786},
{"learn":[38.9938609],"iteration":149,"passed_time":2.699513682,"remaining_time":15.2972442},
{"learn":[38.97399962],"iteration":150,"passed_time":2.717174507,"remaining_time":15.27735865},
{"learn":[38.95851666],"iteration":151,"passed_time":2.735085263,"remaining_time":15.25889673},
{"learn":[38.9387766],"iteration":152,"passed_time":2.753258797,"remaining_time":15.24189674},
{"learn":[38.91897445],"iteration":153,"passed_time":2.770669371,"remaining_time":15.22069018},
{"learn":[38.90083755],"iteration":154,"passed_time":2.788879175,"remaining_time":15.2038897},
{"learn":[38.89158425],"iteration":155,"passed_time":2.805984093,"remaining_time":15.18109343},
{"learn":[38.87431285],"iteration":156,"passed_time":2.823593772,"remaining_time":15.16107993},
{"learn":[38.83364636],"iteration":157,"passed_time":2.841431287,"remaining_time":15.14231103},
{"learn":[38.81148542],"iteration":158,"passed_time":2.859732449,"remaining_time":15.12600622},
{"learn":[38.77800407],"iteration":159,"passed_time":2.877695823,"remaining_time":15.10790307},
{"learn":[38.74442323],"iteration":160,"passed_time":2.895362795,"remaining_time":15.08825705},
{"learn":[38.73056029],"iteration":161,"passed_time":2.911444046,"remaining_time":15.06043278},
{"learn":[38.70107027],"iteration":162,"passed_time":2.931555979,"remaining_time":15.05345003},
{"learn":[38.68055097],"iteration":163,"passed_time":2.949896771,"remaining_time":15.03727866},
{"learn":[38.6654092],"iteration":164,"passed_time":2.968207216,"remaining_time":15.02092742},
{"learn":[38.62603085],"iteration":165,"passed_time":2.986491555,"remaining_time":15.00442143},
{"learn":[38.60713023],"iteration":166,"passed_time":3.004677536,"remaining_time":14.98740352},
{"learn":[38.5900967],"iteration":167,"passed_time":3.02437737,"remaining_time":14.97786888},
{"learn":[38.55300285],"iteration":168,"passed_time":3.041469563,"remaining_time":14.95539176},
{"learn":[38.53330748],"iteration":169,"passed_time":3.058873993,"remaining_time":14.93450244},
{"learn":[38.50750834],"iteration":170,"passed_time":3.075772614,"remaining_time":14.91120174},
{"learn":[38.49433875],"iteration":171,"passed_time":3.091978319,"remaining_time":14.88463982},
{"learn":[38.47412195],"iteration":172,"passed_time":3.108359589,"remaining_time":14.85903688},
{"learn":[38.45481345],"iteration":173,"passed_time":3.126247539,"remaining_time":14.84069234},
{"learn":[38.42060873],"iteration":174,"passed_time":3.143794477,"remaining_time":14.82074539},
{"learn":[38.39260446],"iteration":175,"passed_time":3.161259263,"remaining_time":14.8004411},
{"learn":[38.37683055],"iteration":176,"passed_time":3.177774962,"remaining_time":14.7757559},
{"learn":[38.36466642],"iteration":177,"passed_time":3.193326109,"remaining_time":14.74670821},
{"learn":[38.3364627],"iteration":178,"passed_time":3.210479628,"remaining_time":14.72516075},
{"learn":[38.32208676],"iteration":179,"passed_time":3.228274402,"remaining_time":14.70658339},
{"learn":[38.30185245],"iteration":180,"passed_time":3.244859994,"remaining_time":14.68254329},
{"learn":[38.28908716],"iteration":181,"passed_time":3.261146549,"remaining_time":14.65724108},
{"learn":[38.26366026],"iteration":182,"passed_time":3.279062212,"remaining_time":14.63931053},
{"learn":[38.24012265],"iteration":183,"passed_time":3.296396444,"remaining_time":14.61880162},
{"learn":[38.2131839],"iteration":184,"passed_time":3.31377082,"remaining_time":14.59850388},
{"learn":[38.19124454],"iteration":185,"passed_time":3.329836649,"remaining_time":14.57251092},
{"learn":[38.17561218],"iteration":186,"passed_time":3.346499349,"remaining_time":14.54921909},
{"learn":[38.16171728],"iteration":187,"passed_time":3.362345235,"remaining_time":14.52246984},
{"learn":[38.13805338],"iteration":188,"passed_time":3.379597995,"remaining_time":14.50187288},
{"learn":[38.12610545],"iteration":189,"passed_time":3.395866666,"remaining_time":14.47711578},
{"learn":[38.11267477],"iteration":190,"passed_time":3.412206997,"remaining_time":14.4527511},
{"learn":[38.10255808],"iteration":191,"passed_time":3.428892352,"remaining_time":14.42992198},
{"learn":[38.07994228],"iteration":192,"passed_time":3.446436386,"remaining_time":14.41074696},
{"learn":[38.06483401],"iteration":193,"passed_time":3.463235463,"remaining_time":14.38849373},
{"learn":[38.04726332],"iteration":194,"passed_time":3.480425885,"remaining_time":14.36791199},
{"learn":[38.02939014],"iteration":195,"passed_time":3.496870908,"remaining_time":14.3443072},
{"learn":[38.00992532],"iteration":196,"passed_time":3.514508673,"remaining_time":14.32563688},
{"learn":[37.98993294],"iteration":197,"passed_time":3.531220147,"remaining_time":14.30322504},
{"learn":[37.97428638],"iteration":198,"passed_time":3.548335884,"remaining_time":14.28249771},
{"learn":[37.95071051],"iteration":199,"passed_time":3.565074738,"remaining_time":14.26029895},
{"learn":[37.9302664],"iteration":200,"passed_time":3.58231904,"remaining_time":14.24016374},
{"learn":[37.91944857],"iteration":201,"passed_time":3.598474389,"remaining_time":14.21575526},
{"learn":[37.89730394],"iteration":202,"passed_time":3.615996442,"remaining_time":14.19679391},
{"learn":[37.88069905],"iteration":203,"passed_time":3.633907679,"remaining_time":14.17936526},
{"learn":[37.85907198],"iteration":204,"passed_time":3.651117466,"remaining_time":14.15921163},
{"learn":[37.84357598],"iteration":205,"passed_time":3.667408751,"remaining_time":14.13554635},
{"learn":[37.82522949],"iteration":206,"passed_time":3.68511899,"remaining_time":14.11738821},
{"learn":[37.80697235],"iteration":207,"passed_time":3.701959134,"remaining_time":14.09592132},
{"learn":[37.78744634],"iteration":208,"passed_time":3.719262752,"remaining_time":14.07625281},
{"learn":[37.77734217],"iteration":209,"passed_time":3.735612749,"remaining_time":14.05301939},
{"learn":[37.76470128],"iteration":210,"passed_time":3.752353707,"remaining_time":14.03131315},
{"learn":[37.75407194],"iteration":211,"passed_time":3.770607314,"remaining_time":14.01527624},
{"learn":[37.72967713],"iteration":212,"passed_time":3.788183635,"remaining_time":13.99671606},
{"learn":[37.71884837],"iteration":213,"passed_time":3.804903878,"remaining_time":13.97502078},
{"learn":[37.71155496],"iteration":214,"passed_time":3.820796996,"remaining_time":13.95035182},
{"learn":[37.69910454],"iteration":215,"passed_time":3.837401854,"remaining_time":13.92834747},
{"learn":[37.68834485],"iteration":216,"passed_time":3.855544968,"remaining_time":13.91194336},
{"learn":[37.67529297],"iteration":217,"passed_time":3.8729975,"remaining_time":13.89304608},
{"learn":[37.66690007],"iteration":218,"passed_time":3.889954112,"remaining_time":13.87239343},
{"learn":[37.65635074],"iteration":219,"passed_time":3.907162204,"remaining_time":13.852666},
{"learn":[37.64543089],"iteration":220,"passed_time":3.926679209,"remaining_time":13.84110002},
{"learn":[37.62933204],"iteration":221,"passed_time":3.943753549,"remaining_time":13.82090208},
{"learn":[37.61272751],"iteration":222,"passed_time":3.961134671,"remaining_time":13.80180107},
{"learn":[37.59710399],"iteration":223,"passed_time":3.9790928,"remaining_time":13.78471434},
{"learn":[37.58230011],"iteration":224,"passed_time":3.999125654,"remaining_time":13.77476614},
{"learn":[37.56827726],"iteration":225,"passed_time":4.018414753,"remaining_time":13.7621815},
{"learn":[37.55791712],"iteration":226,"passed_time":4.035473158,"remaining_time":13.74194163},
{"learn":[37.5489953],"iteration":227,"passed_time":4.051544659,"remaining_time":13.71838806},
{"learn":[37.53653008],"iteration":228,"passed_time":4.068486051,"remaining_time":13.69782858},
{"learn":[37.52216776],"iteration":229,"passed_time":4.087025828,"remaining_time":13.68265168},
{"learn":[37.51000059],"iteration":230,"passed_time":4.103973139,"remaining_time":13.66214434},
{"learn":[37.5010433],"iteration":231,"passed_time":4.122582692,"remaining_time":13.64717029},
{"learn":[37.49185401],"iteration":232,"passed_time":4.139452649,"remaining_time":13.62643855},
{"learn":[37.4839187],"iteration":233,"passed_time":4.155894272,"remaining_time":13.60433766},
{"learn":[37.47334699],"iteration":234,"passed_time":4.173142707,"remaining_time":13.58491136},
{"learn":[37.46591454],"iteration":235,"passed_time":4.189242767,"remaining_time":13.56178591},
{"learn":[37.45704543],"iteration":236,"passed_time":4.206654369,"remaining_time":13.54294212},
{"learn":[37.44357524],"iteration":237,"passed_time":4.224844359,"remaining_time":13.52660253},
{"learn":[37.42942211],"iteration":238,"passed_time":4.242828681,"remaining_time":13.50959258},
{"learn":[37.41703138],"iteration":239,"passed_time":4.260197851,"remaining_time":13.49062653},
{"learn":[37.40922009],"iteration":240,"passed_time":4.277501936,"remaining_time":13.47146875},
{"learn":[37.39621482],"iteration":241,"passed_time":4.298348448,"remaining_time":13.463422},
{"learn":[37.38602766],"iteration":242,"passed_time":4.315695808,"remaining_time":13.44436924},
{"learn":[37.37081392],"iteration":243,"passed_time":4.334432763,"remaining_time":13.42963594},
{"learn":[37.36186972],"iteration":244,"passed_time":4.351381954,"remaining_time":13.40936072},
{"learn":[37.34945501],"iteration":245,"passed_time":4.368491242,"remaining_time":13.38960324},
{"learn":[37.3348654],"iteration":246,"passed_time":4.386675328,"remaining_time":13.37314381},
{"learn":[37.32505161],"iteration":247,"passed_time":4.403461368,"remaining_time":13.35243125},
{"learn":[37.3144228],"iteration":248,"passed_time":4.42125297,"remaining_time":13.33478305},
{"learn":[37.30410941],"iteration":249,"passed_time":4.437874811,"remaining_time":13.31362443},
{"learn":[37.29451737],"iteration":250,"passed_time":4.455008814,"remaining_time":13.29403029},
{"learn":[37.28518339],"iteration":251,"passed_time":4.471477345,"remaining_time":13.27248037},
{"learn":[37.27492724],"iteration":252,"passed_time":4.488598519,"remaining_time":13.2528976},
{"learn":[37.26436579],"iteration":253,"passed_time":4.505355989,"remaining_time":13.23226602},
{"learn":[37.25510652],"iteration":254,"passed_time":4.523190005,"remaining_time":13.21481001},
{"learn":[37.24158201],"iteration":255,"passed_time":4.54154286,"remaining_time":13.19885894},
{"learn":[37.22488598],"iteration":256,"passed_time":4.558800421,"remaining_time":13.17972262},
{"learn":[37.21669386],"iteration":257,"passed_time":4.575701413,"remaining_time":13.15957538},
{"learn":[37.2033804],"iteration":258,"passed_time":4.596806794,"remaining_time":13.15148198},
{"learn":[37.19473045],"iteration":259,"passed_time":4.614535422,"remaining_time":13.13367774},
{"learn":[37.18742453],"iteration":260,"passed_time":4.631498197,"remaining_time":13.11370562},
{"learn":[37.17286829],"iteration":261,"passed_time":4.650263966,"remaining_time":13.09883514},
{"learn":[37.16370757],"iteration":262,"passed_time":4.667138403,"remaining_time":13.07863499},
{"learn":[37.15295419],"iteration":263,"passed_time":4.684211322,"remaining_time":13.05901338},
{"learn":[37.1466517],"iteration":264,"passed_time":4.700840248,"remaining_time":13.03817956},
{"learn":[37.13791415],"iteration":265,"passed_time":4.717577118,"remaining_time":13.01767521},
{"learn":[37.12573638],"iteration":266,"passed_time":4.734923811,"remaining_time":12.99887323},
{"learn":[37.11511358],"iteration":267,"passed_time":4.751983983,"remaining_time":12.97929954},
{"learn":[37.10765932],"iteration":268,"passed_time":4.768027485,"remaining_time":12.95698175},
{"learn":[37.08845289],"iteration":269,"passed_time":4.787700321,"remaining_time":12.94452309},
{"learn":[37.08005633],"iteration":270,"passed_time":4.810133865,"remaining_time":12.93943759},
{"learn":[37.07281121],"iteration":271,"passed_time":4.827375,"remaining_time":12.92032721},
{"learn":[37.05832997],"iteration":272,"passed_time":4.848583064,"remaining_time":12.91179446},
{"learn":[37.05024559],"iteration":273,"passed_time":4.867966704,"remaining_time":12.89833513},
{"learn":[37.04089543],"iteration":274,"passed_time":4.904194059,"remaining_time":12.92923888},
{"learn":[37.02940416],"iteration":275,"passed_time":4.939674285,"remaining_time":12.95769631},
{"learn":[37.01728835],"iteration":276,"passed_time":4.959037107,"remaining_time":12.94362393},
{"learn":[37.00823043],"iteration":277,"passed_time":4.982113083,"remaining_time":12.939157},
{"learn":[37.00050252],"iteration":278,"passed_time":5.004542974,"remaining_time":12.93288704},
{"learn":[36.9936054],"iteration":279,"passed_time":5.022732353,"remaining_time":12.91559748},
{"learn":[36.98572912],"iteration":280,"passed_time":5.043588054,"remaining_time":12.90512388},
{"learn":[36.97393649],"iteration":281,"passed_time":5.066704854,"remaining_time":12.90033364},
{"learn":[36.96072738],"iteration":282,"passed_time":5.086874253,"remaining_time":12.88794643},
{"learn":[36.95019748],"iteration":283,"passed_time":5.12500097,"remaining_time":12.92077709},
{"learn":[36.94200348],"iteration":284,"passed_time":5.147844359,"remaining_time":12.91476743},
{"learn":[36.92969964],"iteration":285,"passed_time":5.172609414,"remaining_time":12.91343749},
{"learn":[36.92310125],"iteration":286,"passed_time":5.191884629,"remaining_time":12.89830572},
{"learn":[36.91311336],"iteration":287,"passed_time":5.213048858,"remaining_time":12.88781523},
{"learn":[36.90461501],"iteration":288,"passed_time":5.23736954,"remaining_time":12.88501641},
{"learn":[36.89449717],"iteration":289,"passed_time":5.257533903,"remaining_time":12.87189335},
{"learn":[36.88722361],"iteration":290,"passed_time":5.275214345,"remaining_time":12.85267},
{"learn":[36.87854057],"iteration":291,"passed_time":5.292096808,"remaining_time":12.8315224},
{"learn":[36.8699268],"iteration":292,"passed_time":5.307999492,"remaining_time":12.80803973},
{"learn":[36.85699118],"iteration":293,"passed_time":5.325952491,"remaining_time":12.78953217},
{"learn":[36.85144861],"iteration":294,"passed_time":5.341876054,"remaining_time":12.76617837},
{"learn":[36.8442266],"iteration":295,"passed_time":5.358299055,"remaining_time":12.74406262},
{"learn":[36.83582035],"iteration":296,"passed_time":5.374759244,"remaining_time":12.72207323},
{"learn":[36.82790802],"iteration":297,"passed_time":5.391609698,"remaining_time":12.70104029},
{"learn":[36.82184813],"iteration":298,"passed_time":5.407159506,"remaining_time":12.676986},
{"learn":[36.81428935],"iteration":299,"passed_time":5.423895841,"remaining_time":12.65575696},
{"learn":[36.80775382],"iteration":300,"passed_time":5.439839554,"remaining_time":12.6327171},
{"learn":[36.79924304],"iteration":301,"passed_time":5.45635934,"remaining_time":12.61105569},
{"learn":[36.79323884],"iteration":302,"passed_time":5.472340476,"remaining_time":12.58818915},
{"learn":[36.78528583],"iteration":303,"passed_time":5.488744161,"remaining_time":12.56633532},
{"learn":[36.77870436],"iteration":304,"passed_time":5.505272946,"remaining_time":12.54480229},
{"learn":[36.77086159],"iteration":305,"passed_time":5.521901523,"remaining_time":12.52352829},
{"learn":[36.76302387],"iteration":306,"passed_time":5.538800655,"remaining_time":12.50289529},
{"learn":[36.74821825],"iteration":307,"passed_time":5.555827877,"remaining_time":12.48257432},
{"learn":[36.73900823],"iteration":308,"passed_time":5.57276919,"remaining_time":12.46208256},
{"learn":[36.72725388],"iteration":309,"passed_time":5.590371753,"remaining_time":12.44308552},
{"learn":[36.71847319],"iteration":310,"passed_time":5.606410999,"remaining_time":12.42063401},
{"learn":[36.71100558],"iteration":311,"passed_time":5.622436705,"remaining_time":12.39819376},
{"learn":[36.6995124],"iteration":312,"passed_time":5.640353597,"remaining_time":12.37994544},
{"learn":[36.69361978],"iteration":313,"passed_time":5.659205644,"remaining_time":12.36374227},
{"learn":[36.68683758],"iteration":314,"passed_time":5.675048022,"remaining_time":12.34097745},
{"learn":[36.67985765],"iteration":315,"passed_time":5.692269546,"remaining_time":12.32124168},
{"learn":[36.67050517],"iteration":316,"passed_time":5.709809672,"remaining_time":12.30220822},
{"learn":[36.66277666],"iteration":317,"passed_time":5.72827369,"remaining_time":12.28516559},
{"learn":[36.65540571],"iteration":318,"passed_time":5.744973279,"remaining_time":12.26434734},
{"learn":[36.64844308],"iteration":319,"passed_time":5.762537546,"remaining_time":12.24539228},
{"learn":[36.63943476],"iteration":320,"passed_time":5.78090391,"remaining_time":12.22814254},
{"learn":[36.63337486],"iteration":321,"passed_time":5.797802634,"remaining_time":12.20779561},
{"learn":[36.62579468],"iteration":322,"passed_time":5.815431306,"remaining_time":12.18899998},
{"learn":[36.61865636],"iteration":323,"passed_time":5.831962034,"remaining_time":12.16792079},
{"learn":[36.61191796],"iteration":324,"passed_time":5.850923637,"remaining_time":12.15191832},
{"learn":[36.59425668],"iteration":325,"passed_time":5.87130669,"remaining_time":12.13883653},
{"learn":[36.58695857],"iteration":326,"passed_time":5.888372061,"remaining_time":12.11888195},
{"learn":[36.57889167],"iteration":327,"passed_time":5.904540701,"remaining_time":12.09710778},
{"learn":[36.56813917],"iteration":328,"passed_time":5.924586677,"remaining_time":12.08327556},
{"learn":[36.55977454],"iteration":329,"passed_time":5.940817941,"remaining_time":12.06166067},
{"learn":[36.55316533],"iteration":330,"passed_time":5.957331602,"remaining_time":12.04064907},
{"learn":[36.5446844],"iteration":331,"passed_time":5.974439509,"remaining_time":12.02086022},
{"learn":[36.53640084],"iteration":332,"passed_time":5.991176301,"remaining_time":12.00034412},
{"learn":[36.5279983],"iteration":333,"passed_time":6.008331967,"remaining_time":11.9806859},
{"learn":[36.51836063],"iteration":334,"passed_time":6.024649104,"remaining_time":11.95937807},
{"learn":[36.51188337],"iteration":335,"passed_time":6.040856241,"remaining_time":11.93788257},
{"learn":[36.50588382],"iteration":336,"passed_time":6.05692366,"remaining_time":11.91614358},
{"learn":[36.4937121],"iteration":337,"passed_time":6.074851928,"remaining_time":11.89808277},
{"learn":[36.48682238],"iteration":338,"passed_time":6.09050246,"remaining_time":11.87558149},
{"learn":[36.48065043],"iteration":339,"passed_time":6.106346454,"remaining_time":11.85349606},
{"learn":[36.47260561],"iteration":340,"passed_time":6.122941898,"remaining_time":11.83289945},
{"learn":[36.46278368],"iteration":341,"passed_time":6.140285652,"remaining_time":11.81376596},
{"learn":[36.45794293],"iteration":342,"passed_time":6.156608403,"remaining_time":11.79268723},
{"learn":[36.44890591],"iteration":343,"passed_time":6.173043469,"remaining_time":11.77185034},
{"learn":[36.43805975],"iteration":344,"passed_time":6.190422825,"remaining_time":11.75283174},
{"learn":[36.42687431],"iteration":345,"passed_time":6.207448937,"remaining_time":11.73315493},
{"learn":[36.41983523],"iteration":346,"passed_time":6.224414261,"remaining_time":11.713379},
{"learn":[36.41158156],"iteration":347,"passed_time":6.243429978,"remaining_time":11.69746076},
{"learn":[36.40495712],"iteration":348,"passed_time":6.261105978,"remaining_time":11.67902576},
{"learn":[36.39932229],"iteration":349,"passed_time":6.279039008,"remaining_time":11.66107244},
{"learn":[36.39461231],"iteration":350,"passed_time":6.297865896,"remaining_time":11.64477198},
{"learn":[36.38761959],"iteration":351,"passed_time":6.316124013,"remaining_time":11.62741011},
{"learn":[36.38256348],"iteration":352,"passed_time":6.332598899,"remaining_time":11.60677475},
{"learn":[36.37397498],"iteration":353,"passed_time":6.350094913,"remaining_time":11.58802631},
{"learn":[36.36268677],"iteration":354,"passed_time":6.368377097,"remaining_time":11.57071332},
{"learn":[36.35701047],"iteration":355,"passed_time":6.387417295,"remaining_time":11.55476612},
{"learn":[36.35090846],"iteration":356,"passed_time":6.407939778,"remaining_time":11.54147136},
{"learn":[36.34380557],"iteration":357,"passed_time":6.425338689,"remaining_time":11.52253474},
{"learn":[36.33463172],"iteration":358,"passed_time":6.461707855,"remaining_time":11.53747837},
{"learn":[36.32788614],"iteration":359,"passed_time":6.488155204,"remaining_time":11.53449814},
{"learn":[36.32205716],"iteration":360,"passed_time":6.513901635,"remaining_time":11.53014722},
{"learn":[36.3173674],"iteration":361,"passed_time":6.530944321,"remaining_time":11.51033833},
{"learn":[36.31053833],"iteration":362,"passed_time":6.548015764,"remaining_time":11.49059516},
{"learn":[36.30044339],"iteration":363,"passed_time":6.565922771,"remaining_time":11.4723266},
{"learn":[36.29289471],"iteration":364,"passed_time":6.584706441,"remaining_time":11.45558518},
{"learn":[36.28377592],"iteration":365,"passed_time":6.603078565,"remaining_time":11.4381197},
{"learn":[36.27238051],"iteration":366,"passed_time":6.621589477,"remaining_time":11.42088866},
{"learn":[36.26466321],"iteration":367,"passed_time":6.639321794,"remaining_time":11.40231352},
{"learn":[36.25271881],"iteration":368,"passed_time":6.658816718,"remaining_time":11.38675704},
{"learn":[36.24474562],"iteration":369,"passed_time":6.676096268,"remaining_time":11.36740716},
{"learn":[36.23787154],"iteration":370,"passed_time":6.693471453,"remaining_time":11.34823058},
{"learn":[36.22557894],"iteration":371,"passed_time":6.714229229,"remaining_time":11.33477407},
{"learn":[36.21696381],"iteration":372,"passed_time":6.73717407,"remaining_time":11.3249548},
{"learn":[36.21089821],"iteration":373,"passed_time":6.756630878,"remaining_time":11.30922709},
{"learn":[36.20285772],"iteration":374,"passed_time":6.776288617,"remaining_time":11.29381436},
{"learn":[36.19685006],"iteration":375,"passed_time":6.795094594,"remaining_time":11.2769655},
{"learn":[36.19042008],"iteration":376,"passed_time":6.813260846,"remaining_time":11.25904909},
{"learn":[36.18146618],"iteration":377,"passed_time":6.831516601,"remaining_time":11.24127864},
{"learn":[36.17603661],"iteration":378,"passed_time":6.848592611,"remaining_time":11.22157259},
{"learn":[36.16884135],"iteration":379,"passed_time":6.870709595,"remaining_time":11.21010513},
{"learn":[36.16162551],"iteration":380,"passed_time":6.888418548,"remaining_time":11.19142016},
{"learn":[36.15628087],"iteration":381,"passed_time":6.906845183,"remaining_time":11.17390137},
{"learn":[36.14833061],"iteration":382,"passed_time":6.927157122,"remaining_time":11.159415},
{"learn":[36.13750707],"iteration":383,"passed_time":6.946092177,"remaining_time":11.14268953},
{"learn":[36.12927256],"iteration":384,"passed_time":6.963261245,"remaining_time":11.1231316},
{"learn":[36.11971065],"iteration":385,"passed_time":6.989923485,"remaining_time":11.11868658},
{"learn":[36.11204343],"iteration":386,"passed_time":7.012503804,"remaining_time":11.10766106},
{"learn":[36.10390316],"iteration":387,"passed_time":7.034207046,"remaining_time":11.09519256},
{"learn":[36.09895237],"iteration":388,"passed_time":7.05391307,"remaining_time":11.07953955},
{"learn":[36.09353601],"iteration":389,"passed_time":7.074769199,"remaining_time":11.06566465},
{"learn":[36.08443853],"iteration":390,"passed_time":7.094276848,"remaining_time":11.04965371},
{"learn":[36.07732048],"iteration":391,"passed_time":7.112080596,"remaining_time":11.03098215},
{"learn":[36.06587406],"iteration":392,"passed_time":7.133465506,"remaining_time":11.01784621},
{"learn":[36.05868985],"iteration":393,"passed_time":7.150768422,"remaining_time":10.99839001},
{"learn":[36.05317485],"iteration":394,"passed_time":7.169722696,"remaining_time":10.981474},
{"learn":[36.04272672],"iteration":395,"passed_time":7.188776604,"remaining_time":10.96469967},
{"learn":[36.03285523],"iteration":396,"passed_time":7.208048318,"remaining_time":10.94824467},
{"learn":[36.02643464],"iteration":397,"passed_time":7.225648222,"remaining_time":10.92924681},
{"learn":[36.02202286],"iteration":398,"passed_time":7.246307978,"remaining_time":10.9148649},
{"learn":[36.01522909],"iteration":399,"passed_time":7.26766759,"remaining_time":10.90150138},
{"learn":[36.0093082],"iteration":400,"passed_time":7.286459134,"remaining_time":10.8842619},
{"learn":[36.00464933],"iteration":401,"passed_time":7.303513669,"remaining_time":10.86443078},
{"learn":[35.99902687],"iteration":402,"passed_time":7.321925436,"remaining_time":10.84662403},
{"learn":[35.99163126],"iteration":403,"passed_time":7.341946926,"remaining_time":10.83118903},
{"learn":[35.98233602],"iteration":404,"passed_time":7.361343038,"remaining_time":10.81481261},
{"learn":[35.97639884],"iteration":405,"passed_time":7.383986502,"remaining_time":10.80317237},
{"learn":[35.97059696],"iteration":406,"passed_time":7.400828415,"remaining_time":10.78302518},
{"learn":[35.9637713],"iteration":407,"passed_time":7.418965288,"remaining_time":10.76477316},
{"learn":[35.95746862],"iteration":408,"passed_time":7.435655956,"remaining_time":10.74443196},
{"learn":[35.95254967],"iteration":409,"passed_time":7.454936518,"remaining_time":10.72783548},
{"learn":[35.94690554],"iteration":410,"passed_time":7.471620914,"remaining_time":10.7075054},
{"learn":[35.93601976],"iteration":411,"passed_time":7.491523656,"remaining_time":10.69178619},
{"learn":[35.93029586],"iteration":412,"passed_time":7.509623503,"remaining_time":10.67348425},
{"learn":[35.92551672],"iteration":413,"passed_time":7.527031367,"remaining_time":10.65420382},
{"learn":[35.92147433],"iteration":414,"passed_time":7.544399942,"remaining_time":10.63487703},
{"learn":[35.91227779],"iteration":415,"passed_time":7.563774955,"remaining_time":10.61837638},
{"learn":[35.90483985],"iteration":416,"passed_time":7.580901203,"remaining_time":10.59871799},
{"learn":[35.89944848],"iteration":417,"passed_time":7.598123901,"remaining_time":10.57920601},
{"learn":[35.89292308],"iteration":418,"passed_time":7.615065993,"remaining_time":10.55931585},
{"learn":[35.88321995],"iteration":419,"passed_time":7.631568531,"remaining_time":10.53883273},
{"learn":[35.87514224],"iteration":420,"passed_time":7.649515795,"remaining_time":10.52035545},
{"learn":[35.86906289],"iteration":421,"passed_time":7.684441654,"remaining_time":10.52513572},
{"learn":[35.85893286],"iteration":422,"passed_time":7.731434049,"remaining_time":10.54618782},
{"learn":[35.85314969],"iteration":423,"passed_time":7.758267916,"remaining_time":10.53953377},
{"learn":[35.8457299],"iteration":424,"passed_time":7.785612273,"remaining_time":10.53347543},
{"learn":[35.84122161],"iteration":425,"passed_time":7.803342273,"remaining_time":10.51436259},
{"learn":[35.83514792],"iteration":426,"passed_time":7.839072581,"remaining_time":10.51941121},
{"learn":[35.83044155],"iteration":427,"passed_time":7.856437342,"remaining_time":10.49972467},
{"learn":[35.82332629],"iteration":428,"passed_time":7.881564713,"remaining_time":10.490381},
{"learn":[35.81497935],"iteration":429,"passed_time":7.902082725,"remaining_time":10.47485385},
{"learn":[35.80587995],"iteration":430,"passed_time":7.931543212,"remaining_time":10.47110925},
{"learn":[35.79962094],"iteration":431,"passed_time":7.950965502,"remaining_time":10.45404723},
{"learn":[35.79464163],"iteration":432,"passed_time":7.973945756,"remaining_time":10.44163336},
{"learn":[35.78707519],"iteration":433,"passed_time":7.992341166,"remaining_time":10.42319147},
{"learn":[35.77985094],"iteration":434,"passed_time":8.011210409,"remaining_time":10.40536524},
{"learn":[35.77086775],"iteration":435,"passed_time":8.028628746,"remaining_time":10.38565737},
{"learn":[35.76223392],"iteration":436,"passed_time":8.04835392,"remaining_time":10.36893194},
{"learn":[35.75543932],"iteration":437,"passed_time":8.065479447,"remaining_time":10.34885719},
{"learn":[35.74553726],"iteration":438,"passed_time":8.083133903,"remaining_time":10.3294718},
{"learn":[35.73953182],"iteration":439,"passed_time":8.101078323,"remaining_time":10.31046332},
{"learn":[35.73262841],"iteration":440,"passed_time":8.119027029,"remaining_time":10.2914651},
{"learn":[35.72627336],"iteration":441,"passed_time":8.137137698,"remaining_time":10.2726761},
{"learn":[35.71927257],"iteration":442,"passed_time":8.154632609,"remaining_time":10.25311594},
{"learn":[35.71241076],"iteration":443,"passed_time":8.1725981,"remaining_time":10.23415438},
{"learn":[35.70612475],"iteration":444,"passed_time":8.189958256,"remaining_time":10.21444232},
{"learn":[35.70128952],"iteration":445,"passed_time":8.206467234,"remaining_time":10.19368351},
{"learn":[35.6946163],"iteration":446,"passed_time":8.224222616,"remaining_time":10.1744857},
{"learn":[35.68919344],"iteration":447,"passed_time":8.240856961,"remaining_time":10.15391304},
{"learn":[35.68311781],"iteration":448,"passed_time":8.257420109,"remaining_time":10.13327056},
{"learn":[35.67819963],"iteration":449,"passed_time":8.274056163,"remaining_time":10.11273531},
{"learn":[35.66874652],"iteration":450,"passed_time":8.292310692,"remaining_time":10.09418752},
{"learn":[35.65874567],"iteration":451,"passed_time":8.310273596,"remaining_time":10.07528746},
{"learn":[35.65309754],"iteration":452,"passed_time":8.328940268,"remaining_time":10.05724134},
{"learn":[35.6416744],"iteration":453,"passed_time":8.34729407,"remaining_time":10.03881622},
{"learn":[35.63728015],"iteration":454,"passed_time":8.364935512,"remaining_time":10.01953814},
{"learn":[35.62903584],"iteration":455,"passed_time":8.382803101,"remaining_time":10.00053703},
{"learn":[35.61907455],"iteration":456,"passed_time":8.401189819,"remaining_time":9.982157706},
{"learn":[35.61363436],"iteration":457,"passed_time":8.418110156,"remaining_time":9.962043023},
{"learn":[35.60725884],"iteration":458,"passed_time":8.434755828,"remaining_time":9.941618525},
{"learn":[35.60183862],"iteration":459,"passed_time":8.452095399,"remaining_time":9.922025034},
{"learn":[35.59140905],"iteration":460,"passed_time":8.469892668,"remaining_time":9.90297646},
{"learn":[35.58679547],"iteration":461,"passed_time":8.486438703,"remaining_time":9.882476238},
{"learn":[35.58188943],"iteration":462,"passed_time":8.503424197,"remaining_time":9.862502795},
{"learn":[35.57385156],"iteration":463,"passed_time":8.521393893,"remaining_time":9.843679152},
{"learn":[35.56570285],"iteration":464,"passed_time":8.540019855,"remaining_time":9.825614242},
{"learn":[35.56018314],"iteration":465,"passed_time":8.556343231,"remaining_time":9.804908338},
{"learn":[35.55428301],"iteration":466,"passed_time":8.573103567,"remaining_time":9.784719917},
{"learn":[35.54468407],"iteration":467,"passed_time":8.590962865,"remaining_time":9.765795393},
{"learn":[35.53876247],"iteration":468,"passed_time":8.608200341,"remaining_time":9.746171388},
{"learn":[35.53290221],"iteration":469,"passed_time":8.626409829,"remaining_time":9.727653637},
{"learn":[35.52650435],"iteration":470,"passed_time":8.645240911,"remaining_time":9.709835333},
{"learn":[35.5193487],"iteration":471,"passed_time":8.662329414,"remaining_time":9.690063412},
{"learn":[35.51462733],"iteration":472,"passed_time":8.68023667,"remaining_time":9.671215063},
{"learn":[35.50848291],"iteration":473,"passed_time":8.696875727,"remaining_time":9.65096336},
{"learn":[35.49985982],"iteration":474,"passed_time":8.714217055,"remaining_time":9.631503061},
{"learn":[35.49190977],"iteration":475,"passed_time":8.731668532,"remaining_time":9.612172922},
{"learn":[35.48540011],"iteration":476,"passed_time":8.748445391,"remaining_time":9.592110984},
{"learn":[35.47878967],"iteration":477,"passed_time":8.765483879,"remaining_time":9.572348504},
{"learn":[35.47073941],"iteration":478,"passed_time":8.792636966,"remaining_time":9.563598871},
{"learn":[35.4631492],"iteration":479,"passed_time":8.823759479,"remaining_time":9.559072769},
{"learn":[35.45901309],"iteration":480,"passed_time":8.842309783,"remaining_time":9.540870639},
{"learn":[35.45305965],"iteration":481,"passed_time":8.871554303,"remaining_time":9.534160018},
{"learn":[35.44708421],"iteration":482,"passed_time":8.8898459,"remaining_time":9.515632154},
{"learn":[35.44302255],"iteration":483,"passed_time":8.918153666,"remaining_time":9.507783661},
{"learn":[35.43537862],"iteration":484,"passed_time":8.943129919,"remaining_time":9.496313213},
{"learn":[35.43030752],"iteration":485,"passed_time":8.963814846,"remaining_time":9.480248623},
{"learn":[35.4245799],"iteration":486,"passed_time":8.989697381,"remaining_time":9.469640157},
{"learn":[35.4171883],"iteration":487,"passed_time":9.01251691,"remaining_time":9.455755447},
{"learn":[35.41099936],"iteration":488,"passed_time":9.044712763,"remaining_time":9.451632355},
{"learn":[35.40711279],"iteration":489,"passed_time":9.066381899,"remaining_time":9.436438303},
{"learn":[35.40097677],"iteration":490,"passed_time":9.088707567,"remaining_time":9.421898476},
{"learn":[35.39545929],"iteration":491,"passed_time":9.10591554,"remaining_time":9.402042875},
{"learn":[35.39079218],"iteration":492,"passed_time":9.127892208,"remaining_time":9.387102128},
{"learn":[35.37862287],"iteration":493,"passed_time":9.147371619,"remaining_time":9.369574978},
{"learn":[35.3734388],"iteration":494,"passed_time":9.167005693,"remaining_time":9.352197727},
{"learn":[35.36664062],"iteration":495,"passed_time":9.186131743,"remaining_time":9.334295158},
{"learn":[35.36034195],"iteration":496,"passed_time":9.203772784,"remaining_time":9.314884729},
{"learn":[35.354301],"iteration":497,"passed_time":9.222886213,"remaining_time":9.29696562},
{"learn":[35.34729477],"iteration":498,"passed_time":9.243027816,"remaining_time":9.28007402},
{"learn":[35.34231751],"iteration":499,"passed_time":9.262775205,"remaining_time":9.262775205},
{"learn":[35.33768382],"iteration":500,"passed_time":9.279680624,"remaining_time":9.242635991},
{"learn":[35.33195749],"iteration":501,"passed_time":9.298768447,"remaining_time":9.224674675},
{"learn":[35.32702786],"iteration":502,"passed_time":9.319035239,"remaining_time":9.207873785},
{"learn":[35.31715645],"iteration":503,"passed_time":9.338410721,"remaining_time":9.19018198},
{"learn":[35.31239605],"iteration":504,"passed_time":9.35883204,"remaining_time":9.173508633},
{"learn":[35.30352213],"iteration":505,"passed_time":9.377140176,"remaining_time":9.154757405},
{"learn":[35.29743653],"iteration":506,"passed_time":9.397459165,"remaining_time":9.137963251},
{"learn":[35.28910341],"iteration":507,"passed_time":9.418280007,"remaining_time":9.121641266},
{"learn":[35.28269896],"iteration":508,"passed_time":9.438305444,"remaining_time":9.104534328},
{"learn":[35.27825657],"iteration":509,"passed_time":9.457465802,"remaining_time":9.08658479},
{"learn":[35.27380653],"iteration":510,"passed_time":9.480181651,"remaining_time":9.072032931},
{"learn":[35.26430672],"iteration":511,"passed_time":9.500067911,"remaining_time":9.054752228},
{"learn":[35.25447816],"iteration":512,"passed_time":9.521526977,"remaining_time":9.03895446},
{"learn":[35.25029065],"iteration":513,"passed_time":9.540698025,"remaining_time":9.020971285},
{"learn":[35.24137524],"iteration":514,"passed_time":9.561013016,"remaining_time":9.004060802},
{"learn":[35.23455376],"iteration":515,"passed_time":9.583076817,"remaining_time":8.98877748},
{"learn":[35.22836638],"iteration":516,"passed_time":9.603139964,"remaining_time":8.971598845},
{"learn":[35.22364122],"iteration":517,"passed_time":9.621905356,"remaining_time":8.953201509},
{"learn":[35.21589715],"iteration":518,"passed_time":9.642063327,"remaining_time":8.936093372},
{"learn":[35.20717649],"iteration":519,"passed_time":9.664018081,"remaining_time":8.920632075},
{"learn":[35.20175937],"iteration":520,"passed_time":9.681139008,"remaining_time":8.900701698},
{"learn":[35.19457046],"iteration":521,"passed_time":9.703758045,"remaining_time":8.885816754},
{"learn":[35.18907189],"iteration":522,"passed_time":9.723814522,"remaining_time":8.868565061},
{"learn":[35.18526527],"iteration":523,"passed_time":9.744079557,"remaining_time":8.851492117},
{"learn":[35.18002304],"iteration":524,"passed_time":9.760851722,"remaining_time":8.831246796},
{"learn":[35.17366301],"iteration":525,"passed_time":9.784513869,"remaining_time":8.817223524},
{"learn":[35.17005067],"iteration":526,"passed_time":9.801961156,"remaining_time":8.797585629},
{"learn":[35.16644386],"iteration":527,"passed_time":9.820310902,"remaining_time":8.778762776},
{"learn":[35.16178427],"iteration":528,"passed_time":9.836899921,"remaining_time":8.758374032},
{"learn":[35.1569556],"iteration":529,"passed_time":9.854485166,"remaining_time":8.738883072},
{"learn":[35.14776401],"iteration":530,"passed_time":9.872779676,"remaining_time":8.72002574},
{"learn":[35.14201498],"iteration":531,"passed_time":9.891766274,"remaining_time":8.701779354},
{"learn":[35.13525057],"iteration":532,"passed_time":9.909253245,"remaining_time":8.682216258},
{"learn":[35.13009495],"iteration":533,"passed_time":9.92617346,"remaining_time":8.662166353},
{"learn":[35.12593899],"iteration":534,"passed_time":9.94360874,"remaining_time":8.64257582},
{"learn":[35.12036067],"iteration":535,"passed_time":9.961011055,"remaining_time":8.622964794},
{"learn":[35.11459497],"iteration":536,"passed_time":9.979039863,"remaining_time":8.603902154},
{"learn":[35.10844168],"iteration":537,"passed_time":9.998107628,"remaining_time":8.585735546},
{"learn":[35.10329536],"iteration":538,"passed_time":10.01472693,"remaining_time":8.565471456},
{"learn":[35.09782826],"iteration":539,"passed_time":10.031413,"remaining_time":8.545277737},
{"learn":[35.09059959],"iteration":540,"passed_time":10.04833613,"remaining_time":8.525298124},
{"learn":[35.08492367],"iteration":541,"passed_time":10.06570844,"remaining_time":8.505709346},
{"learn":[35.07941467],"iteration":542,"passed_time":10.08240902,"remaining_time":8.485563395},
{"learn":[35.07370372],"iteration":543,"passed_time":10.09849033,"remaining_time":8.464911012},
{"learn":[35.07032362],"iteration":544,"passed_time":10.11396635,"remaining_time":8.443770074},
{"learn":[35.06555018],"iteration":545,"passed_time":10.13032492,"remaining_time":8.423383728},
{"learn":[35.05776233],"iteration":546,"passed_time":10.14756759,"remaining_time":8.403744277},
{"learn":[35.05122876],"iteration":547,"passed_time":10.1651141,"remaining_time":8.384364189},
{"learn":[35.04615664],"iteration":548,"passed_time":10.18133314,"remaining_time":8.363900264},
{"learn":[35.04172666],"iteration":549,"passed_time":10.19805059,"remaining_time":8.34385957},
{"learn":[35.0362646],"iteration":550,"passed_time":10.21588631,"remaining_time":8.324742205},
{"learn":[35.02842502],"iteration":551,"passed_time":10.23325657,"remaining_time":8.305251706},
{"learn":[35.02451942],"iteration":552,"passed_time":10.24880877,"remaining_time":8.284299315},
{"learn":[35.01773202],"iteration":553,"passed_time":10.26553929,"remaining_time":8.264315023},
{"learn":[35.01389762],"iteration":554,"passed_time":10.28157586,"remaining_time":8.243786046},
{"learn":[35.01009172],"iteration":555,"passed_time":10.29960972,"remaining_time":8.224868193},
{"learn":[35.00559639],"iteration":556,"passed_time":10.31708863,"remaining_time":8.205512143},
{"learn":[34.99949711],"iteration":557,"passed_time":10.33352688,"remaining_time":8.1853385},
{"learn":[34.99190766],"iteration":558,"passed_time":10.35250693,"remaining_time":8.167183467},
{"learn":[34.98658652],"iteration":559,"passed_time":10.36995232,"remaining_time":8.147819679},
{"learn":[34.97785576],"iteration":560,"passed_time":10.38804064,"remaining_time":8.128965852},
{"learn":[34.9695517],"iteration":561,"passed_time":10.40543643,"remaining_time":8.109575012},
{"learn":[34.9613148],"iteration":562,"passed_time":10.42541111,"remaining_time":8.092192993},
{"learn":[34.95487138],"iteration":563,"passed_time":10.44222227,"remaining_time":8.07235622},
{"learn":[34.95055325],"iteration":564,"passed_time":10.45780106,"remaining_time":8.051581351},
{"learn":[34.9464257],"iteration":565,"passed_time":10.47483261,"remaining_time":8.031938788},
{"learn":[34.94011018],"iteration":566,"passed_time":10.49046811,"remaining_time":8.011239312},
{"learn":[34.93708286],"iteration":567,"passed_time":10.50617627,"remaining_time":7.990612939},
{"learn":[34.92976965],"iteration":568,"passed_time":10.52392503,"remaining_time":7.971549537},
{"learn":[34.92455007],"iteration":569,"passed_time":10.53997501,"remaining_time":7.95120922},
{"learn":[34.91771882],"iteration":570,"passed_time":10.5577968,"remaining_time":7.932215111},
{"learn":[34.91275677],"iteration":571,"passed_time":10.57422388,"remaining_time":7.912181505},
{"learn":[34.90342172],"iteration":572,"passed_time":10.59137804,"remaining_time":7.892702311},
{"learn":[34.89581559],"iteration":573,"passed_time":10.60875472,"remaining_time":7.873396358},
{"learn":[34.89154029],"iteration":574,"passed_time":10.62548841,"remaining_time":7.853621869},
{"learn":[34.88731819],"iteration":575,"passed_time":10.64392143,"remaining_time":7.835108828},
{"learn":[34.88341557],"iteration":576,"passed_time":10.66074832,"remaining_time":7.81541861},
{"learn":[34.87656649],"iteration":577,"passed_time":10.67965215,"remaining_time":7.797254686},
{"learn":[34.87014302],"iteration":578,"passed_time":10.69577777,"remaining_time":7.777068119},
{"learn":[34.86587347],"iteration":579,"passed_time":10.71188848,"remaining_time":7.756884762},
{"learn":[34.85853369],"iteration":580,"passed_time":10.72894833,"remaining_time":7.737399914},
{"learn":[34.85299529],"iteration":581,"passed_time":10.74592312,"remaining_time":7.717862313},
{"learn":[34.84504517],"iteration":582,"passed_time":10.76263314,"remaining_time":7.698144114},
{"learn":[34.84046762],"iteration":583,"passed_time":10.77874387,"remaining_time":7.678009331},
{"learn":[34.83476841],"iteration":584,"passed_time":10.79515775,"remaining_time":7.658103362},
{"learn":[34.82721463],"iteration":585,"passed_time":10.81183588,"remaining_time":7.638395996},
{"learn":[34.82365983],"iteration":586,"passed_time":10.827761,"remaining_time":7.618169157},
{"learn":[34.82046276],"iteration":587,"passed_time":10.84550109,"remaining_time":7.599228655},
{"learn":[34.8140478],"iteration":588,"passed_time":10.86228202,"remaining_time":7.579622937},
{"learn":[34.80716891],"iteration":589,"passed_time":10.87871871,"remaining_time":7.559787576},
{"learn":[34.79891996],"iteration":590,"passed_time":10.89592133,"remaining_time":7.540493783},
{"learn":[34.79430628],"iteration":591,"passed_time":10.91272318,"remaining_time":7.520930839},
{"learn":[34.78674314],"iteration":592,"passed_time":10.9304605,"remaining_time":7.502019264},
{"learn":[34.78131675],"iteration":593,"passed_time":10.94709443,"remaining_time":7.482357473},
{"learn":[34.77579936],"iteration":594,"passed_time":10.96346882,"remaining_time":7.462529198},
{"learn":[34.77212643],"iteration":595,"passed_time":10.97963072,"remaining_time":7.442568478},
{"learn":[34.76615117],"iteration":596,"passed_time":10.99596838,"remaining_time":7.422739124},
{"learn":[34.76002377],"iteration":597,"passed_time":11.01250533,"remaining_time":7.40305542},
{"learn":[34.75293196],"iteration":598,"passed_time":11.02897085,"remaining_time":7.383334407},
{"learn":[34.74604988],"iteration":599,"passed_time":11.04628672,"remaining_time":7.364191144},
{"learn":[34.73912161],"iteration":600,"passed_time":11.06335309,"remaining_time":7.344888321},
{"learn":[34.73216291],"iteration":601,"passed_time":11.07986814,"remaining_time":7.325228435},
{"learn":[34.72729744],"iteration":602,"passed_time":11.09608024,"remaining_time":7.305379531},
{"learn":[34.72092744],"iteration":603,"passed_time":11.11285211,"remaining_time":7.285909665},
{"learn":[34.71689665],"iteration":604,"passed_time":11.12815594,"remaining_time":7.265490244},
{"learn":[34.71013731],"iteration":605,"passed_time":11.14496031,"remaining_time":7.246063302},
{"learn":[34.70515291],"iteration":606,"passed_time":11.16233633,"remaining_time":7.22701512},
{"learn":[34.70018897],"iteration":607,"passed_time":11.17762674,"remaining_time":7.206627767},
{"learn":[34.6941436],"iteration":608,"passed_time":11.19508974,"remaining_time":7.187652035},
{"learn":[34.68983446],"iteration":609,"passed_time":11.21118958,"remaining_time":7.167809728},
{"learn":[34.68268109],"iteration":610,"passed_time":11.22854561,"remaining_time":7.148779448},
{"learn":[34.67901506],"iteration":611,"passed_time":11.24439809,"remaining_time":7.128801404},
{"learn":[34.67240357],"iteration":612,"passed_time":11.26135036,"remaining_time":7.109531141},
{"learn":[34.66765861],"iteration":613,"passed_time":11.2779312,"remaining_time":7.090034921},
{"learn":[34.66154051],"iteration":614,"passed_time":11.29671208,"remaining_time":7.07192545},
{"learn":[34.6555385],"iteration":615,"passed_time":11.31281689,"remaining_time":7.052145596},
{"learn":[34.65183177],"iteration":616,"passed_time":11.32909676,"remaining_time":7.032486319},
{"learn":[34.64796084],"iteration":617,"passed_time":11.34670352,"remaining_time":7.01365816},
{"learn":[34.64247554],"iteration":618,"passed_time":11.37235565,"remaining_time":6.99978595},
{"learn":[34.63573887],"iteration":619,"passed_time":11.39074715,"remaining_time":6.981425673},
{"learn":[34.62981379],"iteration":620,"passed_time":11.40814209,"remaining_time":6.962457088},
{"learn":[34.62430184],"iteration":621,"passed_time":11.43360518,"remaining_time":6.948396718},
{"learn":[34.61989974],"iteration":622,"passed_time":11.45042488,"remaining_time":6.929069312},
{"learn":[34.61395887],"iteration":623,"passed_time":11.47068237,"remaining_time":6.911821428},
{"learn":[34.60885964],"iteration":624,"passed_time":11.4927723,"remaining_time":6.895663382},
{"learn":[34.60463105],"iteration":625,"passed_time":11.51390532,"remaining_time":6.87891468},
{"learn":[34.60018688],"iteration":626,"passed_time":11.53006926,"remaining_time":6.85919591},
{"learn":[34.59341227],"iteration":627,"passed_time":11.54631868,"remaining_time":6.839539089},
{"learn":[34.58794913],"iteration":628,"passed_time":11.56295994,"remaining_time":6.820124227},
{"learn":[34.58020897],"iteration":629,"passed_time":11.58004334,"remaining_time":6.800977834},
{"learn":[34.57432393],"iteration":630,"passed_time":11.59617106,"remaining_time":6.781279116},
{"learn":[34.57007062],"iteration":631,"passed_time":11.61256032,"remaining_time":6.761743983},
{"learn":[34.56018331],"iteration":632,"passed_time":11.63033751,"remaining_time":6.743023486},
{"learn":[34.55149149],"iteration":633,"passed_time":11.64692539,"remaining_time":6.723619389},
{"learn":[34.547458],"iteration":634,"passed_time":11.66419276,"remaining_time":6.704614734},
{"learn":[34.54249351],"iteration":635,"passed_time":11.67981304,"remaining_time":6.68467287},
{"learn":[34.53335407],"iteration":636,"passed_time":11.69680605,"remaining_time":6.665526841},
{"learn":[34.52638225],"iteration":637,"passed_time":11.71265986,"remaining_time":6.645741173},
{"learn":[34.52017796],"iteration":638,"passed_time":11.73028086,"remaining_time":6.626966182},
{"learn":[34.51295196],"iteration":639,"passed_time":11.7472585,"remaining_time":6.607832909},
{"learn":[34.50722738],"iteration":640,"passed_time":11.76478241,"remaining_time":6.589012302},
{"learn":[34.50329903],"iteration":641,"passed_time":11.78066354,"remaining_time":6.56927967},
{"learn":[34.4996799],"iteration":642,"passed_time":11.7971313,"remaining_time":6.549884717},
{"learn":[34.4923814],"iteration":643,"passed_time":11.81369703,"remaining_time":6.530553018},
{"learn":[34.48466574],"iteration":644,"passed_time":11.83110129,"remaining_time":6.51169141},
{"learn":[34.47867485],"iteration":645,"passed_time":11.84847506,"remaining_time":6.492817603},
{"learn":[34.4711955],"iteration":646,"passed_time":11.86534165,"remaining_time":6.473671719},
{"learn":[34.46407709],"iteration":647,"passed_time":11.88196605,"remaining_time":6.45440131},
{"learn":[34.45855948],"iteration":648,"passed_time":11.89801996,"remaining_time":6.434830519},
{"learn":[34.45441925],"iteration":649,"passed_time":11.91420793,"remaining_time":6.41534273},
{"learn":[34.44975819],"iteration":650,"passed_time":11.93253514,"remaining_time":6.397011926},
{"learn":[34.4461029],"iteration":651,"passed_time":11.94836406,"remaining_time":6.377347689},
{"learn":[34.43907914],"iteration":652,"passed_time":11.96517943,"remaining_time":6.358219393},
{"learn":[34.43444938],"iteration":653,"passed_time":11.98120664,"remaining_time":6.33868119},
{"learn":[34.43169886],"iteration":654,"passed_time":11.99749681,"remaining_time":6.319292213},
{"learn":[34.42332588],"iteration":655,"passed_time":12.01464546,"remaining_time":6.300362864},
{"learn":[34.41531495],"iteration":656,"passed_time":12.03245504,"remaining_time":6.281783988},
{"learn":[34.40800742],"iteration":657,"passed_time":12.05003421,"remaining_time":6.263087688},
{"learn":[34.40331707],"iteration":658,"passed_time":12.06599628,"remaining_time":6.243558015},
{"learn":[34.39961927],"iteration":659,"passed_time":12.0817366,"remaining_time":6.223924914},
{"learn":[34.39188229],"iteration":660,"passed_time":12.09858616,"remaining_time":6.204872479},
{"learn":[34.38474923],"iteration":661,"passed_time":12.11561877,"remaining_time":6.185920159},
{"learn":[34.37780825],"iteration":662,"passed_time":12.13272161,"remaining_time":6.167009323},
{"learn":[34.37264727],"iteration":663,"passed_time":12.14920272,"remaining_time":6.147789331},
{"learn":[34.36953692],"iteration":664,"passed_time":12.16601791,"remaining_time":6.128745863},
{"learn":[34.36250154],"iteration":665,"passed_time":12.1899618,"remaining_time":6.113284146},
{"learn":[34.3559174],"iteration":666,"passed_time":12.21369062,"remaining_time":6.097689619},
{"learn":[34.35038447],"iteration":667,"passed_time":12.23659646,"remaining_time":6.081661713},
{"learn":[34.34601837],"iteration":668,"passed_time":12.25606688,"remaining_time":6.063913508},
{"learn":[34.34071875],"iteration":669,"passed_time":12.27905889,"remaining_time":6.047894675},
{"learn":[34.33430035],"iteration":670,"passed_time":12.29778967,"remaining_time":6.029765725},
{"learn":[34.3264991],"iteration":671,"passed_time":12.3166024,"remaining_time":6.01167498},
{"learn":[34.32079626],"iteration":672,"passed_time":12.33725979,"remaining_time":5.99447838},
{"learn":[34.31268744],"iteration":673,"passed_time":12.35752109,"remaining_time":5.977079936},
{"learn":[34.30800139],"iteration":674,"passed_time":12.37795687,"remaining_time":5.959757013},
{"learn":[34.3037241],"iteration":675,"passed_time":12.39705109,"remaining_time":5.941781886},
{"learn":[34.29659467],"iteration":676,"passed_time":12.42206762,"remaining_time":5.926629014},
{"learn":[34.29353262],"iteration":677,"passed_time":12.44170199,"remaining_time":5.908890915},
{"learn":[34.2870413],"iteration":678,"passed_time":12.46063028,"remaining_time":5.890813433},
{"learn":[34.2783917],"iteration":679,"passed_time":12.48366734,"remaining_time":5.874666983},
{"learn":[34.27362184],"iteration":680,"passed_time":12.50509387,"remaining_time":5.857745881},
{"learn":[34.26541522],"iteration":681,"passed_time":12.52488299,"remaining_time":5.840048082},
{"learn":[34.25913008],"iteration":682,"passed_time":12.54419497,"remaining_time":5.8221227},
{"learn":[34.25493879],"iteration":683,"passed_time":12.56135209,"remaining_time":5.803197749},
{"learn":[34.24998999],"iteration":684,"passed_time":12.58519931,"remaining_time":5.787354429},
{"learn":[34.24459472],"iteration":685,"passed_time":12.60274586,"remaining_time":5.768603791},
{"learn":[34.23739173],"iteration":686,"passed_time":12.62771791,"remaining_time":5.753239746},
{"learn":[34.22993987],"iteration":687,"passed_time":12.65134691,"remaining_time":5.737238717},
{"learn":[34.22150661],"iteration":688,"passed_time":12.67345841,"remaining_time":5.720530574},
{"learn":[34.21528094],"iteration":689,"passed_time":12.69456333,"remaining_time":5.703354539},
{"learn":[34.20910859],"iteration":690,"passed_time":12.71128287,"remaining_time":5.684206087},
{"learn":[34.2018961],"iteration":691,"passed_time":12.73498645,"remaining_time":5.668173158},
{"learn":[34.19607035],"iteration":692,"passed_time":12.75652735,"remaining_time":5.651160024},
{"learn":[34.19043551],"iteration":693,"passed_time":12.78107767,"remaining_time":5.635460759},
{"learn":[34.18578906],"iteration":694,"passed_time":12.79915408,"remaining_time":5.616894954},
{"learn":[34.17881838],"iteration":695,"passed_time":12.82401785,"remaining_time":5.601295154},
{"learn":[34.1740754],"iteration":696,"passed_time":12.84310728,"remaining_time":5.583158544},
{"learn":[34.16953457],"iteration":697,"passed_time":12.86304386,"remaining_time":5.565385739},
{"learn":[34.16633068],"iteration":698,"passed_time":12.88031126,"remaining_time":5.546457353},
{"learn":[34.15878376],"iteration":699,"passed_time":12.90070144,"remaining_time":5.528872046},
{"learn":[34.15280449],"iteration":700,"passed_time":12.91899085,"remaining_time":5.510382688},
{"learn":[34.14847652],"iteration":701,"passed_time":12.9396841,"remaining_time":5.492914332},
{"learn":[34.14438845],"iteration":702,"passed_time":12.95835309,"remaining_time":5.474581605},
{"learn":[34.14074359],"iteration":703,"passed_time":12.97454827,"remaining_time":5.455207796},
{"learn":[34.13453476],"iteration":704,"passed_time":12.99232214,"remaining_time":5.436503592},
{"learn":[34.13070443],"iteration":705,"passed_time":13.00984637,"remaining_time":5.417698064},
{"learn":[34.12380119],"iteration":706,"passed_time":13.026033,"remaining_time":5.398341822},
{"learn":[34.11892485],"iteration":707,"passed_time":13.04507168,"remaining_time":5.380170806},
{"learn":[34.11244279],"iteration":708,"passed_time":13.06197943,"remaining_time":5.361122729},
{"learn":[34.10498701],"iteration":709,"passed_time":13.07863008,"remaining_time":5.341975668},
{"learn":[34.10026701],"iteration":710,"passed_time":13.09537196,"remaining_time":5.32287271},
{"learn":[34.09310277],"iteration":711,"passed_time":13.112082,"remaining_time":5.303763504},
{"learn":[34.08877392],"iteration":712,"passed_time":13.12949445,"remaining_time":5.28494377},
{"learn":[34.08581054],"iteration":713,"passed_time":13.14464024,"remaining_time":5.265220041},
{"learn":[34.07984338],"iteration":714,"passed_time":13.16154803,"remaining_time":5.246211454},
{"learn":[34.07294622],"iteration":715,"passed_time":13.17788511,"remaining_time":5.226982361},
{"learn":[34.06731077],"iteration":716,"passed_time":13.19419463,"remaining_time":5.207750462},
{"learn":[34.05889026],"iteration":717,"passed_time":13.21128875,"remaining_time":5.188834856},
{"learn":[34.05278624],"iteration":718,"passed_time":13.22656162,"remaining_time":5.16921254},
{"learn":[34.04703777],"iteration":719,"passed_time":13.24245166,"remaining_time":5.149842312},
{"learn":[34.04223614],"iteration":720,"passed_time":13.26168274,"remaining_time":5.131774596},
{"learn":[34.03853379],"iteration":721,"passed_time":13.27766615,"remaining_time":5.112453172},
{"learn":[34.03452312],"iteration":722,"passed_time":13.29363384,"remaining_time":5.093134957},
{"learn":[34.02731636],"iteration":723,"passed_time":13.31091974,"remaining_time":5.07432852},
{"learn":[34.02087599],"iteration":724,"passed_time":13.32757212,"remaining_time":5.055285975},
{"learn":[34.01690984],"iteration":725,"passed_time":13.34325611,"remaining_time":5.035884537},
{"learn":[34.01103701],"iteration":726,"passed_time":13.36391164,"remaining_time":5.018360215},
{"learn":[34.00647866],"iteration":727,"passed_time":13.38037497,"remaining_time":4.999260977},
{"learn":[34.001663],"iteration":728,"passed_time":13.39743158,"remaining_time":4.980389516},
{"learn":[33.99633109],"iteration":729,"passed_time":13.41395261,"remaining_time":4.961324939},
{"learn":[33.99213888],"iteration":730,"passed_time":13.43035449,"remaining_time":4.942223471},
{"learn":[33.98777255],"iteration":731,"passed_time":13.45024031,"remaining_time":4.924404922},
{"learn":[33.98188699],"iteration":732,"passed_time":13.47256178,"remaining_time":4.907467935},
{"learn":[33.97613399],"iteration":733,"passed_time":13.49495356,"remaining_time":4.890541752},
{"learn":[33.97091617],"iteration":734,"passed_time":13.51191284,"remaining_time":4.871642044},
{"learn":[33.96534514],"iteration":735,"passed_time":13.53213236,"remaining_time":4.853917043},
{"learn":[33.95996446],"iteration":736,"passed_time":13.54929339,"remaining_time":4.83509384},
{"learn":[33.95464577],"iteration":737,"passed_time":13.56730953,"remaining_time":4.816578722},
{"learn":[33.95010942],"iteration":738,"passed_time":13.58822572,"remaining_time":4.799089193},
{"learn":[33.94585852],"iteration":739,"passed_time":13.60626782,"remaining_time":4.780580586},
{"learn":[33.94189271],"iteration":740,"passed_time":13.62219143,"remaining_time":4.761332767},
{"learn":[33.93566242],"iteration":741,"passed_time":13.63822415,"remaining_time":4.742131846},
{"learn":[33.92928482],"iteration":742,"passed_time":13.65504864,"remaining_time":4.723213324},
{"learn":[33.92455326],"iteration":743,"passed_time":13.67130217,"remaining_time":4.704103974},
{"learn":[33.9162763],"iteration":744,"passed_time":13.68864497,"remaining_time":4.685375123},
{"learn":[33.90845368],"iteration":745,"passed_time":13.70549246,"remaining_time":4.666481347},
{"learn":[33.90173927],"iteration":746,"passed_time":13.72471389,"remaining_time":4.648397073},
{"learn":[33.89343141],"iteration":747,"passed_time":13.74269514,"remaining_time":4.629891946},
{"learn":[33.88583372],"iteration":748,"passed_time":13.76259658,"remaining_time":4.612031698},
{"learn":[33.8799116],"iteration":749,"passed_time":13.77870412,"remaining_time":4.592901374},
{"learn":[33.87202228],"iteration":750,"passed_time":13.80025092,"remaining_time":4.57558253},
{"learn":[33.86868042],"iteration":751,"passed_time":13.81676814,"remaining_time":4.556593748},
{"learn":[33.86314134],"iteration":752,"passed_time":13.83295146,"remaining_time":4.537502007},
{"learn":[33.85845946],"iteration":753,"passed_time":13.84869434,"remaining_time":4.51827428},
{"learn":[33.85181624],"iteration":754,"passed_time":13.86681266,"remaining_time":4.499826624},
{"learn":[33.84628325],"iteration":755,"passed_time":13.88338547,"remaining_time":4.480881024},
{"learn":[33.83899345],"iteration":756,"passed_time":13.90005185,"remaining_time":4.461971729},
{"learn":[33.83486609],"iteration":757,"passed_time":13.91649837,"remaining_time":4.442998159},
{"learn":[33.8272408],"iteration":758,"passed_time":13.94010444,"remaining_time":4.426304571},
{"learn":[33.82340191],"iteration":759,"passed_time":13.95782181,"remaining_time":4.407733204},
{"learn":[33.8184343],"iteration":760,"passed_time":13.9813613,"remaining_time":4.390992577},
{"learn":[33.81229556],"iteration":761,"passed_time":14.00414405,"remaining_time":4.373997746},
{"learn":[33.80861958],"iteration":762,"passed_time":14.02773453,"remaining_time":4.357238641},
{"learn":[33.80275144],"iteration":763,"passed_time":14.04676662,"remaining_time":4.339053562},
{"learn":[33.79582047],"iteration":764,"passed_time":14.06840023,"remaining_time":4.32166543},
{"learn":[33.79078207],"iteration":765,"passed_time":14.0848424,"remaining_time":4.302680316},
{"learn":[33.78483568],"iteration":766,"passed_time":14.1047966,"remaining_time":4.28476872},
{"learn":[33.77979149],"iteration":767,"passed_time":14.12241462,"remaining_time":4.266146082},
{"learn":[33.77618785],"iteration":768,"passed_time":14.14206873,"remaining_time":4.248137681},
{"learn":[33.77002687],"iteration":769,"passed_time":14.1593471,"remaining_time":4.229415368},
{"learn":[33.76367448],"iteration":770,"passed_time":14.1804215,"remaining_time":4.211824285},
{"learn":[33.75958587],"iteration":771,"passed_time":14.19672249,"remaining_time":4.192814413},
{"learn":[33.75427184],"iteration":772,"passed_time":14.2150113,"remaining_time":4.174395296},
{"learn":[33.7484656],"iteration":773,"passed_time":14.23529687,"remaining_time":4.156559552},
{"learn":[33.74367098],"iteration":774,"passed_time":14.25417002,"remaining_time":4.138307425},
{"learn":[33.73613618],"iteration":775,"passed_time":14.27336165,"remaining_time":4.120145631},
{"learn":[33.73047944],"iteration":776,"passed_time":14.29335429,"remaining_time":4.102211076},
{"learn":[33.72313362],"iteration":777,"passed_time":14.31139983,"remaining_time":4.083715632},
{"learn":[33.71909834],"iteration":778,"passed_time":14.33881555,"remaining_time":4.067879636},
{"learn":[33.71541959],"iteration":779,"passed_time":14.35972828,"remaining_time":4.05017977},
{"learn":[33.70685284],"iteration":780,"passed_time":14.38271322,"remaining_time":4.033052747},
{"learn":[33.70249493],"iteration":781,"passed_time":14.40238531,"remaining_time":4.014987208},
{"learn":[33.696016],"iteration":782,"passed_time":14.42093937,"remaining_time":3.996607717},
{"learn":[33.68969909],"iteration":783,"passed_time":14.44044877,"remaining_time":3.978490986},
{"learn":[33.6843124],"iteration":784,"passed_time":14.45679521,"remaining_time":3.95950442},
{"learn":[33.68203425],"iteration":785,"passed_time":14.48091736,"remaining_time":3.942641623},
{"learn":[33.67698298],"iteration":786,"passed_time":14.5002036,"remaining_time":3.924451546},
{"learn":[33.67046076],"iteration":787,"passed_time":14.53106361,"remaining_time":3.909372442},
{"learn":[33.66496981],"iteration":788,"passed_time":14.54909247,"remaining_time":3.890821941},
{"learn":[33.65963201],"iteration":789,"passed_time":14.57566747,"remaining_time":3.874544518},
{"learn":[33.65227327],"iteration":790,"passed_time":14.59961573,"remaining_time":3.857547013},
{"learn":[33.64595266],"iteration":791,"passed_time":14.62276066,"remaining_time":3.840320981},
{"learn":[33.64177012],"iteration":792,"passed_time":14.64208211,"remaining_time":3.822081962},
{"learn":[33.63385848],"iteration":793,"passed_time":14.66382382,"remaining_time":3.804468146},
{"learn":[33.62834403],"iteration":794,"passed_time":14.68303171,"remaining_time":3.786190566},
{"learn":[33.62365077],"iteration":795,"passed_time":14.70182186,"remaining_time":3.767803593},
{"learn":[33.61890302],"iteration":796,"passed_time":14.72301655,"remaining_time":3.750028055},
{"learn":[33.61192313],"iteration":797,"passed_time":14.74052483,"remaining_time":3.731310796},
{"learn":[33.60302138],"iteration":798,"passed_time":14.76048052,"remaining_time":3.713212247},
{"learn":[33.59740955],"iteration":799,"passed_time":14.7788038,"remaining_time":3.694700951},
{"learn":[33.59166707],"iteration":800,"passed_time":14.79826997,"remaining_time":3.676474062},
{"learn":[33.58575136],"iteration":801,"passed_time":14.81628883,"remaining_time":3.657886768},
{"learn":[33.57879731],"iteration":802,"passed_time":14.83389058,"remaining_time":3.639198562},
{"learn":[33.57202251],"iteration":803,"passed_time":14.85300447,"remaining_time":3.620881688},
{"learn":[33.56851133],"iteration":804,"passed_time":14.86990431,"remaining_time":3.602026509},
{"learn":[33.56262261],"iteration":805,"passed_time":14.8879872,"remaining_time":3.583460938},
{"learn":[33.55606465],"iteration":806,"passed_time":14.90691721,"remaining_time":3.56509916},
{"learn":[33.55220456],"iteration":807,"passed_time":14.924511,"remaining_time":3.546418457},
{"learn":[33.54637152],"iteration":808,"passed_time":14.94209016,"remaining_time":3.527736984},
{"learn":[33.54315853],"iteration":809,"passed_time":14.96546713,"remaining_time":3.510418216},
{"learn":[33.53739653],"iteration":810,"passed_time":14.98512422,"remaining_time":3.492217605},
{"learn":[33.53412737],"iteration":811,"passed_time":15.00322381,"remaining_time":3.473652803},
{"learn":[33.52852216],"iteration":812,"passed_time":15.02404975,"remaining_time":3.45571624},
{"learn":[33.52253186],"iteration":813,"passed_time":15.04361651,"remaining_time":3.437484854},
{"learn":[33.51853154],"iteration":814,"passed_time":15.06172441,"remaining_time":3.418919037},
{"learn":[33.51317667],"iteration":815,"passed_time":15.07879653,"remaining_time":3.400120787},
{"learn":[33.50737009],"iteration":816,"passed_time":15.1002356,"remaining_time":3.382304914},
{"learn":[33.50244],"iteration":817,"passed_time":15.11868591,"remaining_time":3.363815202},
{"learn":[33.49887948],"iteration":818,"passed_time":15.13877049,"remaining_time":3.345686763},
{"learn":[33.49073794],"iteration":819,"passed_time":15.15703656,"remaining_time":3.327154367},
{"learn":[33.48482638],"iteration":820,"passed_time":15.17855628,"remaining_time":3.309332003},
{"learn":[33.47697336],"iteration":821,"passed_time":15.19598782,"remaining_time":3.290615367},
{"learn":[33.47222076],"iteration":822,"passed_time":15.21392043,"remaining_time":3.272009618},
{"learn":[33.46691031],"iteration":823,"passed_time":15.23241403,"remaining_time":3.253525326},
{"learn":[33.46314429],"iteration":824,"passed_time":15.24982585,"remaining_time":3.234811545},
{"learn":[33.45596403],"iteration":825,"passed_time":15.27134142,"remaining_time":3.216965384},
{"learn":[33.45085563],"iteration":826,"passed_time":15.28877058,"remaining_time":3.198255515},
{"learn":[33.44541212],"iteration":827,"passed_time":15.30966633,"remaining_time":3.180268852},
{"learn":[33.4403731],"iteration":828,"passed_time":15.32801977,"remaining_time":3.161750761},
{"learn":[33.43273074],"iteration":829,"passed_time":15.34861689,"remaining_time":3.143692615},
{"learn":[33.43010703],"iteration":830,"passed_time":15.3655499,"remaining_time":3.124883192},
{"learn":[33.42668838],"iteration":831,"passed_time":15.38505748,"remaining_time":3.106598144},
{"learn":[33.42241817],"iteration":832,"passed_time":15.40275201,"remaining_time":3.087946681},
{"learn":[33.41787135],"iteration":833,"passed_time":15.42206913,"remaining_time":3.069620475},
{"learn":[33.41251532],"iteration":834,"passed_time":15.44200586,"remaining_time":3.051414332},
{"learn":[33.40619027],"iteration":835,"passed_time":15.46042519,"remaining_time":3.032906377},
{"learn":[33.4009065],"iteration":836,"passed_time":15.47897325,"remaining_time":3.014423703},
{"learn":[33.39241705],"iteration":837,"passed_time":15.4965143,"remaining_time":2.9957462},
{"learn":[33.38627764],"iteration":838,"passed_time":15.51376436,"remaining_time":2.977015568},
{"learn":[33.38260975],"iteration":839,"passed_time":15.53098777,"remaining_time":2.958283385},
{"learn":[33.37457743],"iteration":840,"passed_time":15.54836762,"remaining_time":2.939584366},
{"learn":[33.36996059],"iteration":841,"passed_time":15.56412296,"remaining_time":2.920583644},
{"learn":[33.36353693],"iteration":842,"passed_time":15.58098759,"remaining_time":2.901797214},
{"learn":[33.35787301],"iteration":843,"passed_time":15.59724331,"remaining_time":2.882902791},
{"learn":[33.35328504],"iteration":844,"passed_time":15.61338153,"remaining_time":2.863993062},
{"learn":[33.34648363],"iteration":845,"passed_time":15.63065422,"remaining_time":2.845296394},
{"learn":[33.33946746],"iteration":846,"passed_time":15.64833943,"remaining_time":2.826677606},
{"learn":[33.33588516],"iteration":847,"passed_time":15.6644649,"remaining_time":2.807781445},
{"learn":[33.32900554],"iteration":848,"passed_time":15.68592981,"remaining_time":2.789841462},
{"learn":[33.32217296],"iteration":849,"passed_time":15.70325785,"remaining_time":2.77116315},
{"learn":[33.3157424],"iteration":850,"passed_time":15.72045105,"remaining_time":2.752464402},
{"learn":[33.30967173],"iteration":851,"passed_time":15.73680298,"remaining_time":2.733623054},
{"learn":[33.30353897],"iteration":852,"passed_time":15.75352588,"remaining_time":2.71485147},
{"learn":[33.29894855],"iteration":853,"passed_time":15.77067636,"remaining_time":2.696157785},
{"learn":[33.29419055],"iteration":854,"passed_time":15.78613961,"remaining_time":2.677181572},
{"learn":[33.28624891],"iteration":855,"passed_time":15.80310427,"remaining_time":2.658466138},
{"learn":[33.28154138],"iteration":856,"passed_time":15.81911372,"remaining_time":2.639595405},
{"learn":[33.27911831],"iteration":857,"passed_time":15.83573155,"remaining_time":2.620832027},
{"learn":[33.27349373],"iteration":858,"passed_time":15.85266827,"remaining_time":2.602125991},
{"learn":[33.26619037],"iteration":859,"passed_time":15.86945487,"remaining_time":2.583399631},
{"learn":[33.26091178],"iteration":860,"passed_time":15.88586836,"remaining_time":2.56461754},
{"learn":[33.25522181],"iteration":861,"passed_time":15.90338897,"remaining_time":2.546018188},
{"learn":[33.24825769],"iteration":862,"passed_time":15.92004021,"remaining_time":2.527283324},
{"learn":[33.2409754],"iteration":863,"passed_time":15.93763186,"remaining_time":2.508701312},
{"learn":[33.23432397],"iteration":864,"passed_time":15.95447708,"remaining_time":2.490005093},
{"learn":[33.22827871],"iteration":865,"passed_time":15.97143071,"remaining_time":2.471329925},
{"learn":[33.22413639],"iteration":866,"passed_time":15.9872653,"remaining_time":2.452487065},
{"learn":[33.21835209],"iteration":867,"passed_time":16.00400293,"remaining_time":2.433788464},
{"learn":[33.21442074],"iteration":868,"passed_time":16.02011089,"remaining_time":2.414999455},
{"learn":[33.21048592],"iteration":869,"passed_time":16.03656664,"remaining_time":2.396268578},
{"learn":[33.20700086],"iteration":870,"passed_time":16.05182976,"remaining_time":2.377366291},
{"learn":[33.20049035],"iteration":871,"passed_time":16.07036359,"remaining_time":2.358952454},
{"learn":[33.19435436],"iteration":872,"passed_time":16.08732064,"remaining_time":2.340308959},
{"learn":[33.18927502],"iteration":873,"passed_time":16.10671303,"remaining_time":2.322020414},
{"learn":[33.1815337],"iteration":874,"passed_time":16.1233377,"remaining_time":2.303333957},
{"learn":[33.17716908],"iteration":875,"passed_time":16.13952191,"remaining_time":2.284589859},
{"learn":[33.17122804],"iteration":876,"passed_time":16.15553477,"remaining_time":2.265827568},
{"learn":[33.16741344],"iteration":877,"passed_time":16.17289804,"remaining_time":2.247259181},
{"learn":[33.16350283],"iteration":878,"passed_time":16.18840606,"remaining_time":2.22843815},
{"learn":[33.1570567],"iteration":879,"passed_time":16.20505706,"remaining_time":2.209780508},
{"learn":[33.14998664],"iteration":880,"passed_time":16.22191932,"remaining_time":2.191155958},
{"learn":[33.14317959],"iteration":881,"passed_time":16.23809573,"remaining_time":2.172443647},
{"learn":[33.13885835],"iteration":882,"passed_time":16.25345117,"remaining_time":2.153628298},
{"learn":[33.13346805],"iteration":883,"passed_time":16.26988213,"remaining_time":2.134961909},
{"learn":[33.12903266],"iteration":884,"passed_time":16.28701873,"remaining_time":2.116392264},
{"learn":[33.12472928],"iteration":885,"passed_time":16.30471031,"remaining_time":2.097897264},
{"learn":[33.11941164],"iteration":886,"passed_time":16.3238626,"remaining_time":2.079590162},
{"learn":[33.1161511],"iteration":887,"passed_time":16.34009811,"remaining_time":2.060913275},
{"learn":[33.11092897],"iteration":888,"passed_time":16.35694177,"remaining_time":2.042317814},
{"learn":[33.1049991],"iteration":889,"passed_time":16.37319704,"remaining_time":2.023653566},
{"learn":[33.09982142],"iteration":890,"passed_time":16.38965276,"remaining_time":2.005019249},
{"learn":[33.09413525],"iteration":891,"passed_time":16.40720665,"remaining_time":1.986522778},
{"learn":[33.08706466],"iteration":892,"passed_time":16.42670648,"remaining_time":1.968261583},
{"learn":[33.08280406],"iteration":893,"passed_time":16.44301515,"remaining_time":1.949619246},
{"learn":[33.07699817],"iteration":894,"passed_time":16.45961109,"remaining_time":1.931015826},
{"learn":[33.07213815],"iteration":895,"passed_time":16.47702201,"remaining_time":1.912511483},
{"learn":[33.06683091],"iteration":896,"passed_time":16.49375585,"remaining_time":1.893931831},
{"learn":[33.06119038],"iteration":897,"passed_time":16.50972667,"remaining_time":1.875269622},
{"learn":[33.05483908],"iteration":898,"passed_time":16.52708272,"remaining_time":1.856769027},
{"learn":[33.04960737],"iteration":899,"passed_time":16.54346006,"remaining_time":1.838162229},
{"learn":[33.04511228],"iteration":900,"passed_time":16.55930701,"remaining_time":1.819502102},
{"learn":[33.0414458],"iteration":901,"passed_time":16.57566425,"remaining_time":1.800903655},
{"learn":[33.0372048],"iteration":902,"passed_time":16.59746037,"remaining_time":1.782894414},
{"learn":[33.03118627],"iteration":903,"passed_time":16.61380963,"remaining_time":1.764298368},
{"learn":[33.02555174],"iteration":904,"passed_time":16.63105072,"remaining_time":1.745800904},
{"learn":[33.01985701],"iteration":905,"passed_time":16.64880242,"remaining_time":1.727359191},
{"learn":[33.01594387],"iteration":906,"passed_time":16.66508583,"remaining_time":1.708768448},
{"learn":[33.01028285],"iteration":907,"passed_time":16.6809808,"remaining_time":1.69014343},
{"learn":[33.00573524],"iteration":908,"passed_time":16.69664801,"remaining_time":1.671501616},
{"learn":[32.99947449],"iteration":909,"passed_time":16.71265601,"remaining_time":1.652900045},
{"learn":[32.99334669],"iteration":910,"passed_time":16.72977383,"remaining_time":1.634412592},
{"learn":[32.98831471],"iteration":911,"passed_time":16.74720113,"remaining_time":1.615958004},
{"learn":[32.98388055],"iteration":912,"passed_time":16.76281045,"remaining_time":1.597332431},
{"learn":[32.97921999],"iteration":913,"passed_time":16.77976917,"remaining_time":1.578840425},
{"learn":[32.97299007],"iteration":914,"passed_time":16.79748706,"remaining_time":1.560422296},
{"learn":[32.96939558],"iteration":915,"passed_time":16.81611797,"remaining_time":1.542089421},
{"learn":[32.9651677],"iteration":916,"passed_time":16.83231418,"remaining_time":1.523535526},
{"learn":[32.95824197],"iteration":917,"passed_time":16.85265646,"remaining_time":1.505357113},
{"learn":[32.95300357],"iteration":918,"passed_time":16.86912465,"remaining_time":1.486832532},
{"learn":[32.94889588],"iteration":919,"passed_time":16.88810932,"remaining_time":1.468531246},
{"learn":[32.94345114],"iteration":920,"passed_time":16.90498895,"remaining_time":1.450047912},
{"learn":[32.93837597],"iteration":921,"passed_time":16.92268134,"remaining_time":1.431636816},
{"learn":[32.93397048],"iteration":922,"passed_time":16.9385148,"remaining_time":1.413072199},
{"learn":[32.92938071],"iteration":923,"passed_time":16.95718207,"remaining_time":1.394746577},
{"learn":[32.92484051],"iteration":924,"passed_time":16.97585779,"remaining_time":1.376420902},
{"learn":[32.92138267],"iteration":925,"passed_time":16.99710899,"remaining_time":1.358300286},
{"learn":[32.91546098],"iteration":926,"passed_time":17.01786132,"remaining_time":1.340133631},
{"learn":[32.91078263],"iteration":927,"passed_time":17.04087895,"remaining_time":1.32213716},
{"learn":[32.90513273],"iteration":928,"passed_time":17.05809174,"remaining_time":1.303686237},
{"learn":[32.90165626],"iteration":929,"passed_time":17.07916413,"remaining_time":1.285528483},
{"learn":[32.89723121],"iteration":930,"passed_time":17.09653592,"remaining_time":1.267090202},
{"learn":[32.89245626],"iteration":931,"passed_time":17.11483109,"remaining_time":1.248721582},
{"learn":[32.88674372],"iteration":932,"passed_time":17.13433088,"remaining_time":1.230439624},
{"learn":[32.88157935],"iteration":933,"passed_time":17.15737484,"remaining_time":1.212405502},
{"learn":[32.87464305],"iteration":934,"passed_time":17.18037003,"remaining_time":1.194357275},
{"learn":[32.86857403],"iteration":935,"passed_time":17.19938363,"remaining_time":1.176026231},
{"learn":[32.86226911],"iteration":936,"passed_time":17.21730924,"remaining_time":1.157620579},
{"learn":[32.85568414],"iteration":937,"passed_time":17.23535866,"remaining_time":1.139224133},
{"learn":[32.8501267],"iteration":938,"passed_time":17.25270878,"remaining_time":1.120782998},
{"learn":[32.84469173],"iteration":939,"passed_time":17.26857954,"remaining_time":1.102249758},
{"learn":[32.83661507],"iteration":940,"passed_time":17.28644749,"remaining_time":1.083847398},
{"learn":[32.83065717],"iteration":941,"passed_time":17.30532869,"remaining_time":1.06550856},
{"learn":[32.82631561],"iteration":942,"passed_time":17.32280772,"remaining_time":1.047083818},
{"learn":[32.82214665],"iteration":943,"passed_time":17.33927422,"remaining_time":1.028601013},
{"learn":[32.81623786],"iteration":944,"passed_time":17.35545325,"remaining_time":1.010105744},
{"learn":[32.8128322],"iteration":945,"passed_time":17.37157677,"remaining_time":0.9916122048},
{"learn":[32.80637784],"iteration":946,"passed_time":17.38879425,"remaining_time":0.9731848949},
{"learn":[32.80171854],"iteration":947,"passed_time":17.40552346,"remaining_time":0.9547333542},
{"learn":[32.79833074],"iteration":948,"passed_time":17.42171262,"remaining_time":0.9362564214},
{"learn":[32.79558436],"iteration":949,"passed_time":17.43782431,"remaining_time":0.9177802267},
{"learn":[32.79095601],"iteration":950,"passed_time":17.45463262,"remaining_time":0.8993448986},
{"learn":[32.78698613],"iteration":951,"passed_time":17.47228821,"remaining_time":0.8809557083},
{"learn":[32.78376753],"iteration":952,"passed_time":17.4879287,"remaining_time":0.8624686769},
{"learn":[32.77854388],"iteration":953,"passed_time":17.50416785,"remaining_time":0.8440164792},
{"learn":[32.77415215],"iteration":954,"passed_time":17.52087225,"remaining_time":0.825590839},
{"learn":[32.76765729],"iteration":955,"passed_time":17.54565498,"remaining_time":0.8075406056},
{"learn":[32.76352438],"iteration":956,"passed_time":17.56432331,"remaining_time":0.7892015699},
{"learn":[32.75909306],"iteration":957,"passed_time":17.58641292,"remaining_time":0.7710118401},
{"learn":[32.74951187],"iteration":958,"passed_time":17.63314593,"remaining_time":0.7538675528},
{"learn":[32.74499392],"iteration":959,"passed_time":17.65145751,"remaining_time":0.7354773962},
{"learn":[32.74081784],"iteration":960,"passed_time":17.67483724,"remaining_time":0.7172930825},
{"learn":[32.73561046],"iteration":961,"passed_time":17.69259913,"remaining_time":0.698876057},
{"learn":[32.72859237],"iteration":962,"passed_time":17.70977334,"remaining_time":0.6804378127},
{"learn":[32.72329953],"iteration":963,"passed_time":17.72884954,"remaining_time":0.6620732192},
{"learn":[32.71876312],"iteration":964,"passed_time":17.75089867,"remaining_time":0.6438149776},
{"learn":[32.71365296],"iteration":965,"passed_time":17.76842813,"remaining_time":0.6253898099},
{"learn":[32.7108255],"iteration":966,"passed_time":17.78958764,"remaining_time":0.6070903743},
{"learn":[32.70813934],"iteration":967,"passed_time":17.81034914,"remaining_time":0.5887718725},
{"learn":[32.70350083],"iteration":968,"passed_time":17.82712404,"remaining_time":0.5703207898},
{"learn":[32.69982235],"iteration":969,"passed_time":17.8459107,"remaining_time":0.5519353824},
{"learn":[32.69436788],"iteration":970,"passed_time":17.86271632,"remaining_time":0.5334899828},
{"learn":[32.69082696],"iteration":971,"passed_time":17.87882618,"remaining_time":0.5150279146},
{"learn":[32.6846889],"iteration":972,"passed_time":17.89767811,"remaining_time":0.4966467719},
{"learn":[32.6803622],"iteration":973,"passed_time":17.91745579,"remaining_time":0.4782893742},
{"learn":[32.67397608],"iteration":974,"passed_time":17.93571017,"remaining_time":0.4598900043},
{"learn":[32.66973508],"iteration":975,"passed_time":17.95575987,"remaining_time":0.4415350787},
{"learn":[32.66520606],"iteration":976,"passed_time":17.97307532,"remaining_time":0.4231123157},
{"learn":[32.65828421],"iteration":977,"passed_time":17.99129778,"remaining_time":0.4047122201},
{"learn":[32.65188386],"iteration":978,"passed_time":18.00806246,"remaining_time":0.3862812173},
{"learn":[32.6476637],"iteration":979,"passed_time":18.02420196,"remaining_time":0.3678408564},
{"learn":[32.64211319],"iteration":980,"passed_time":18.0407053,"remaining_time":0.3494122332},
{"learn":[32.63462947],"iteration":981,"passed_time":18.05807242,"remaining_time":0.3310033642},
{"learn":[32.63119601],"iteration":982,"passed_time":18.07464729,"remaining_time":0.3125829134},
{"learn":[32.62500534],"iteration":983,"passed_time":18.10147744,"remaining_time":0.2943329665},
{"learn":[32.61907467],"iteration":984,"passed_time":18.11888406,"remaining_time":0.2759220922},
{"learn":[32.61428146],"iteration":985,"passed_time":18.13910036,"remaining_time":0.2575531491},
{"learn":[32.6060074],"iteration":986,"passed_time":18.15872369,"remaining_time":0.2391726525},
{"learn":[32.60081697],"iteration":987,"passed_time":18.17502685,"remaining_time":0.220749314},
{"learn":[32.59748835],"iteration":988,"passed_time":18.19183336,"remaining_time":0.2023358614},
{"learn":[32.59194349],"iteration":989,"passed_time":18.20951115,"remaining_time":0.1839344561},
{"learn":[32.58701041],"iteration":990,"passed_time":18.22725666,"remaining_time":0.1655351261},
{"learn":[32.57914627],"iteration":991,"passed_time":18.24463281,"remaining_time":0.1471341356},
{"learn":[32.5733601],"iteration":992,"passed_time":18.26179645,"remaining_time":0.1287337111},
{"learn":[32.56856479],"iteration":993,"passed_time":18.27849948,"remaining_time":0.1103329949},
{"learn":[32.56484189],"iteration":994,"passed_time":18.29502497,"remaining_time":0.09193479885},
{"learn":[32.55779769],"iteration":995,"passed_time":18.3127067,"remaining_time":0.07354500684},
{"learn":[32.55355234],"iteration":996,"passed_time":18.32944982,"remaining_time":0.05515381088},
{"learn":[32.54927237],"iteration":997,"passed_time":18.34656085,"remaining_time":0.03676665501},
{"learn":[32.54565884],"iteration":998,"passed_time":18.36637564,"remaining_time":0.0183847604},
{"learn":[32.5377216],"iteration":999,"passed_time":18.38334292,"remaining_time":0}
]}